Workbook
Name Orders: Orders!$A$1:$U$9995
Name People: People!$A$1:$B$5
Name Returns: Returns!$C$1:$C$801
Name Срез_Category: #N/A
Name Срез_City: #N/A
Name Срез_Region: #N/A
Name Срез_Segment: #N/A
Name Срез_Sub_Category: #N/A
Name Срез_Годы: #N/A

Sheet Orders
A1: Row ID | B1: Order ID | C1: Order Date | D1: Ship Date | E1: Ship Mode | F1: Customer ID | G1: Customer Name | H1: Segment | I1: Country | J1: City | K1: State | L1: Postal Code | M1: Region | N1: Product ID | O1: Category | P1: Sub-Category | Q1: Product Name | R1: Sales | S1: Quantity | T1: Discount | U1: Profit | V1: Person | W1: Returnes | X1: Столбец1
A2: 1 | B2: CA-2018-152156 | C2: 43412 | D2: 43415 | E2: Second Class | F2: CG-12520 | G2: Claire Gute | H2: Consumer | I2: United States | J2: Henderson | K2: Kentucky | L2: 42420 | M2: South | N2: FUR-BO-10001798 | O2: Furniture | P2: Bookcases | Q2: Bush Somerset Collection Bookcase | R2: 261.96 | S2: 2 | T2: 0 | U2: 41.9136 | V2: =IF(M2=People!$B$2, People!$A$2, IF(M2=People!$B$3, People!$A$3, IF(M2=People!$B$4, People!$A$4, IF(M2=People!$B$5, People!$A$5, 0)))) -> Cassandra Brandow | W2: =IFERROR(VLOOKUP(Orders!$B2,Returns!$B:$C,2,0),"No") -> No | X2: =IFERROR((INDEX(Returns!$C$2:$C$801, MATCH(B2, Returns!$B$2:$B$801, 0))), "No") -> No
A3: 2 | B3: CA-2018-152156 | C3: 43412 | D3: 43415 | E3: Second Class | F3: CG-12520 | G3: Claire Gute | H3: Consumer | I3: United States | J3: Henderson | K3: Kentucky | L3: 42420 | M3: South | N3: FUR-CH-10000454 | O3: Furniture | P3: Chairs | Q3: Hon Deluxe Fabric Upholstered Stacking Chairs, Rounded Back | R3: 731.94 | S3: 3 | T3: 0 | U3: 219.582 | V3: =IF(M3=People!$B$2, People!$A$2, IF(M3=People!$B$3, People!$A$3, IF(M3=People!$B$4, People!$A$4, IF(M3=People!$B$5, People!$A$5, 0)))) -> Cassandra Brandow | W3: =IFERROR(VLOOKUP(Orders!$B3,Returns!$B:$C,2,0),"No") -> No | X3: =IFERROR((INDEX(Returns!$C$2:$C$801, MATCH(B3, Returns!$B$2:$B$801, 0))), "No") -> No
A4: 3 | B4: CA-2018-138688 | C4: 43263 | D4: 43267 | E4: Second Class | F4: DV-13045 | G4: Darrin Van Huff | H4: Corporate | I4: United States | J4: Los Angeles | K4: California | L4: 90036 | M4: West | N4: OFF-LA-10000240 | O4: Office Supplies | P4: Labels | Q4: Self-Adhesive Address Labels for Typewriters by Universal | R4: 14.62 | S4: 2 | T4: 0 | U4: 6.8714 | V4: =IF(M4=People!$B$2, People!$A$2, IF(M4=People!$B$3, People!$A$3, IF(M4=People!$B$4, People!$A$4, IF(M4=People!$B$5, People!$A$5, 0)))) -> Anna Andreadi | W4: =IFERROR(VLOOKUP(Orders!$B4,Returns!$B:$C,2,0),"No") -> No | X4: =IFERROR((INDEX(Returns!$C$2:$C$801, MATCH(B4, Returns!$B$2:$B$801, 0))), "No") -> No
A5: 4 | B5: US-2017-108966 | C5: 43019 | D5: 43026 | E5: Standard Class | F5: SO-20335 | G5: Sean O'Donnell | H5: Consumer | I5: United States | J5: Fort Lauderdale | K5: Florida | L5: 33311 | M5: South | N5: FUR-TA-10000577 | O5: Furniture | P5: Tables | Q5: Bretford CR4500 Series Slim Rectangular Table | R5: 957.5775 | S5: 5 | T5: 0.45 | U5: -383.031 | V5: =IF(M5=People!$B$2, People!$A$2, IF(M5=People!$B$3, People!$A$3, IF(M5=People!$B$4, People!$A$4, IF(M5=People!$B$5, People!$A$5, 0)))) -> Cassandra Brandow | W5: =IFERROR(VLOOKUP(Orders!$B5,Returns!$B:$C,2,0),"No") -> No | X5: =IFERROR((INDEX(Returns!$C$2:$C$801, MATCH(B5, Returns!$B$2:$B$801, 0))), "No") -> No
A6: 5 | B6: US-2017-108966 | C6: 43019 | D6: 43026 | E6: Standard Class | F6: SO-20335 | G6: Sean O'Donnell | H6: Consumer | I6: United States | J6: Fort Lauderdale | K6: Florida | L6: 33311 | M6: South | N6: OFF-ST-10000760 | O6: Office Supplies | P6: Storage | Q6: Eldon Fold 'N Roll Cart System | R6: 22.368 | S6: 2 | T6: 0.2 | U6: 2.5164 | V6: =IF(M6=People!$B$2, People!$A$2, IF(M6=People!$B$3, People!$A$3, IF(M6=People!$B$4, People!$A$4, IF(M6=People!$B$5, People!$A$5, 0)))) -> Cassandra Brandow | W6: =IFERROR(VLOOKUP(Orders!$B6,Returns!$B:$C,2,0),"No") -> No | X6: =IFERROR((INDEX(Returns!$C$2:$C$801, MATCH(B6, Returns!$B$2:$B$801, 0))), "No") -> No
A7: 6 | B7: CA-2016-115812 | C7: 42530 | D7: 42535 | E7: Standard Class | F7: BH-11710 | G7: Brosina Hoffman | H7: Consumer | I7: United States | J7: Los Angeles | K7: California | L7: 90032 | M7: West | N7: FUR-FU-10001487 | O7: Furniture | P7: Furnishings | Q7: Eldon Expressions Wood and Plastic Desk Accessories, Cherry Wood | R7: 48.86 | S7: 7 | T7: 0 | U7: 14.1694 | V7: =IF(M7=People!$B$2, People!$A$2, IF(M7=People!$B$3, People!$A$3, IF(M7=People!$B$4, People!$A$4, IF(M7=People!$B$5, People!$A$5, 0)))) -> Anna Andreadi | W7: =IFERROR(VLOOKUP(Orders!$B7,Returns!$B:$C,2,0),"No") -> No | X7: =IFERROR((INDEX(Returns!$C$2:$C$801, MATCH(B7, Returns!$B$2:$B$801, 0))), "No") -> No
A8: 7 | B8: CA-2016-115812 | C8: 42530 | D8: 42535 | E8: Standard Class | F8: BH-11710 | G8: Brosina Hoffman | H8: Consumer | I8: United States | J8: Los Angeles | K8: California | L8: 90032 | M8: West | N8: OFF-AR-10002833 | O8: Office Supplies | P8: Art | Q8: Newell 322 | R8: 7.28 | S8: 4 | T8: 0 | U8: 1.9656 | V8: =IF(M8=People!$B$2, People!$A$2, IF(M8=People!$B$3, People!$A$3, IF(M8=People!$B$4, People!$A$4, IF(M8=People!$B$5, People!$A$5, 0)))) -> Anna Andreadi | W8: =IFERROR(VLOOKUP(Orders!$B8,Returns!$B:$C,2,0),"No") -> No | X8: =IFERROR((INDEX(Returns!$C$2:$C$801, MATCH(B8, Returns!$B$2:$B$801, 0))), "No") -> No
A9: 8 | B9: CA-2016-115812 | C9: 42530 | D9: 42535 | E9: Standard Class | F9: BH-11710 | G9: Brosina Hoffman | H9: Consumer | I9: United States | J9: Los Angeles | K9: California | L9: 90032 | M9: West | N9: TEC-PH-10002275 | O9: Technology | P9: Phones | Q9: Mitel 5320 IP Phone VoIP phone | R9: 907.152 | S9: 6 | T9: 0.2 | U9: 90.7152 | V9: =IF(M9=People!$B$2, People!$A$2, IF(M9=People!$B$3, People!$A$3, IF(M9=People!$B$4, People!$A$4, IF(M9=People!$B$5, People!$A$5, 0)))) -> Anna Andreadi | W9: =IFERROR(VLOOKUP(Orders!$B9,Returns!$B:$C,2,0),"No") -> No | X9: =IFERROR((INDEX(Returns!$C$2:$C$801, MATCH(B9, Returns!$B$2:$B$801, 0))), "No") -> No
A10: 9 | B10: CA-2016-115812 | C10: 42530 | D10: 42535 | E10: Standard Class | F10: BH-11710 | G10: Brosina Hoffman | H10: Consumer | I10: United States | J10: Los Angeles | K10: California | L10: 90032 | M10: West | N10: OFF-BI-10003910 | O10: Office Supplies | P10: Binders | Q10: DXL Angle-View Binders with Locking Rings by Samsill | R10: 18.504 | S10: 3 | T10: 0.2 | U10: 5.7825 | V10: =IF(M10=People!$B$2, People!$A$2, IF(M10=People!$B$3, People!$A$3, IF(M10=People!$B$4, People!$A$4, IF(M10=People!$B$5, People!$A$5, 0)))) -> Anna Andreadi | W10: =IFERROR(VLOOKUP(Orders!$B10,Returns!$B:$C,2,0),"No") -> No | X10: =IFERROR((INDEX(Returns!$C$2:$C$801, MATCH(B10, Returns!$B$2:$B$801, 0))), "No") -> No
A11: 10 | B11: CA-2016-115812 | C11: 42530 | D11: 42535 | E11: Standard Class | F11: BH-11710 | G11: Brosina Hoffman | H11: Consumer | I11: United States | J11: Los Angeles | K11: California | L11: 90032 | M11: West | N11: OFF-AP-10002892 | O11: Office Supplies | P11: Appliances | Q11: Belkin F5C206VTEL 6 Outlet Surge | R11: 114.9 | S11: 5 | T11: 0 | U11: 34.47 | V11: =IF(M11=People!$B$2, People!$A$2, IF(M11=People!$B$3, People!$A$3, IF(M11=People!$B$4, People!$A$4, IF(M11=People!$B$5, People!$A$5, 0)))) -> Anna Andreadi | W11: =IFERROR(VLOOKUP(Orders!$B11,Returns!$B:$C,2,0),"No") -> No | X11: =IFERROR((INDEX(Returns!$C$2:$C$801, MATCH(B11, Returns!$B$2:$B$801, 0))), "No") -> No
A12: 11 | B12: CA-2016-115812 | C12: 42530 | D12: 42535 | E12: Standard Class | F12: BH-11710 | G12: Brosina Hoffman | H12: Consumer | I12: United States | J12: Los Angeles | K12: California | L12: 90032 | M12: West | N12: FUR-TA-10001539 | O12: Furniture | P12: Tables | Q12: Chromcraft Rectangular Conference Tables | R12: 1706.184 | S12: 9 | T12: 0.2 | U12: 85.3092 | V12: =IF(M12=People!$B$2, People!$A$2, IF(M12=People!$B$3, People!$A$3, IF(M12=People!$B$4, People!$A$4, IF(M12=People!$B$5, People!$A$5, 0)))) -> Anna Andreadi | W12: =IFERROR(VLOOKUP(Orders!$B12,Returns!$B:$C,2,0),"No") -> No | X12: =IFERROR((INDEX(Returns!$C$2:$C$801, MATCH(B12, Returns!$B$2:$B$801, 0))), "No") -> No
A13: 12 | B13: CA-2016-115812 | C13: 42530 | D13: 42535 | E13: Standard Class | F13: BH-11710 | G13: Brosina Hoffman | H13: Consumer | I13: United States | J13: Los Angeles | K13: California | L13: 90032 | M13: West | N13: TEC-PH-10002033 | O13: Technology | P13: Phones | Q13: Konftel 250 Conference phone - Charcoal black | R13: 911.424 | S13: 4 | T13: 0.2 | U13: 68.3568 | V13: =IF(M13=People!$B$2, People!$A$2, IF(M13=People!$B$3, People!$A$3, IF(M13=People!$B$4, People!$A$4, IF(M13=People!$B$5, People!$A$5, 0)))) -> Anna Andreadi | W13: =IFERROR(VLOOKUP(Orders!$B13,Returns!$B:$C,2,0),"No") -> No | X13: =IFERROR((INDEX(Returns!$C$2:$C$801, MATCH(B13, Returns!$B$2:$B$801, 0))), "No") -> No
... A2235: 2234 | B2235: CA-2017-123232 | C2235: 43083 | D2235: 43085 | E2235: Second Class | F2235: DJ-13630 | G2235: Doug Jacobs | H2235: Consumer | I2235: United States | J2235: Portland | K2235: Oregon | L2235: 97206 | M2235: West | N2235: TEC-PH-10001051 | O2235: Technology | P2235: Phones | Q2235: HTC One | R2235: 319.968 | S2235: 4 | T2235: 0.2 | U2235: 35.9964 | V2235: =IF(M2235=People!$B$2, People!$A$2, IF(M2235=People!$B$3, People!$A$3, IF(M2235=People!$B$4, People!$A$4, IF(M2235=People!$B$5, People!$A$5, 0)))) -> Anna Andreadi | W2235: =IFERROR(VLOOKUP(Orders!$B2235,Returns!$B:$C,2,0),"No") -> No | X2235: =IFERROR((INDEX(Returns!$C$2:$C$801, MATCH(B2235, Returns!$B$2:$B$801, 0))), "No") -> No
A2236: 2235 | B2236: CA-2019-104066 | C2236: 43804 | D2236: 43809 | E2236: Standard Class | F2236: QJ-19255 | G2236: Quincy Jones | H2236: Corporate | I2236: United States | J2236: Burlington | K2236: Vermont | M2236: East | N2236: TEC-AC-10001013 | O2236: Technology | P2236: Accessories | Q2236: Logitech ClearChat Comfort/USB Headset H390 | R2236: 205.03 | S2236: 7 | T2236: 0 | U2236: 67.6599 | V2236: =IF(M2236=People!$B$2, People!$A$2, IF(M2236=People!$B$3, People!$A$3, IF(M2236=People!$B$4, People!$A$4, IF(M2236=People!$B$5, People!$A$5, 0)))) -> Chuck Magee | W2236: =IFERROR(VLOOKUP(Orders!$B2236,Returns!$B:$C,2,0),"No") -> No | X2236: =IFERROR((INDEX(Returns!$C$2:$C$801, MATCH(B2236, Returns!$B$2:$B$801, 0))), "No") -> No
A2237: 2236 | B2237: CA-2017-145849 | C2237: 42993 | D2237: 42995 | E2237: Second Class | F2237: CT-11995 | G2237: Carol Triggs | H2237: Consumer | I2237: United States | J2237: Indianapolis | K2237: Indiana | L2237: 46203 | M2237: Central | N2237: OFF-ST-10000025 | O2237: Office Supplies | P2237: Storage | Q2237: Fellowes Stor/Drawer Steel Plus Storage Drawers | R2237: 190.86 | S2237: 2 | T2237: 0 | U2237: 11.4516 | V2237: =IF(M2237=People!$B$2, People!$A$2, IF(M2237=People!$B$3, People!$A$3, IF(M2237=People!$B$4, People!$A$4, IF(M2237=People!$B$5, People!$A$5, 0)))) -> Kelly Williams | W2237: =IFERROR(VLOOKUP(Orders!$B2237,Returns!$B:$C,2,0),"No") -> No | X2237: =IFERROR((INDEX(Returns!$C$2:$C$801, MATCH(B2237, Returns!$B$2:$B$801, 0))), "No") -> No
A2238: 2237 | B2238: CA-2017-145849 | C2238: 42993 | D2238: 42995 | E2238: Second Class | F2238: CT-11995 | G2238: Carol Triggs | H2238: Consumer | I2238: United States | J2238: Indianapolis | K2238: Indiana | L2238: 46203 | M2238: Central | N2238: OFF-AR-10000817 | O2238: Office Supplies | P2238: Art | Q2238: Manco Dry-Lighter Erasable Highlighter | R2238: 24.32 | S2238: 8 | T2238: 0 | U2238: 8.2688 | V2238: =IF(M2238=People!$B$2, People!$A$2, IF(M2238=People!$B$3, People!$A$3, IF(M2238=People!$B$4, People!$A$4, IF(M2238=People!$B$5, People!$A$5, 0)))) -> Kelly Williams | W2238: =IFERROR(VLOOKUP(Orders!$B2238,Returns!$B:$C,2,0),"No") -> No | X2238: =IFERROR((INDEX(Returns!$C$2:$C$801, MATCH(B2238, Returns!$B$2:$B$801, 0))), "No") -> No
A2239: 2238 | B2239: CA-2018-122322 | C2239: 43296 | D2239: 43302 | E2239: Standard Class | F2239: RH-19510 | G2239: Rick Huthwaite | H2239: Home Office | I2239: United States | J2239: Provo | K2239: Utah | L2239: 84604 | M2239: West | N2239: OFF-SU-10000952 | O2239: Office Supplies | P2239: Supplies | Q2239: Fiskars Home & Office Scissors | R2239: 44.4 | S2239: 5 | T2239: 0 | U2239: 12.432 | V2239: =IF(M2239=People!$B$2, People!$A$2, IF(M2239=People!$B$3, People!$A$3, IF(M2239=People!$B$4, People!$A$4, IF(M2239=People!$B$5, People!$A$5, 0)))) -> Anna Andreadi | W2239: =IFERROR(VLOOKUP(Orders!$B2239,Returns!$B:$C,2,0),"No") -> No | X2239: =IFERROR((INDEX(Returns!$C$2:$C$801, MATCH(B2239, Returns!$B$2:$B$801, 0))), "No") -> No
A2240: 2239 | B2240: CA-2019-166849 | C2240: 43575 | D2240: 43581 | E2240: Standard Class | F2240: SJ-20125 | G2240: Sanjit Jacobs | H2240: Home Office | I2240: United States | J2240: Chicago | K2240: Illinois | L2240: 60610 | M2240: Central | N2240: FUR-FU-10004597 | O2240: Furniture | P2240: Furnishings | Q2240: Eldon Cleatmat Chair Mats for Medium Pile Carpets | R2240: 44.4 | S2240: 2 | T2240: 0.6 | U2240: -52.17 | V2240: =IF(M2240=People!$B$2, People!$A$2, IF(M2240=People!$B$3, People!$A$3, IF(M2240=People!$B$4, People!$A$4, IF(M2240=People!$B$5, People!$A$5, 0)))) -> Kelly Williams | W2240: =IFERROR(VLOOKUP(Orders!$B2240,Returns!$B:$C,2,0),"No") -> No | X2240: =IFERROR((INDEX(Returns!$C$2:$C$801, MATCH(B2240, Returns!$B$2:$B$801, 0))), "No") -> No
A2241: 2240 | B2241: CA-2018-146633 | C2241: 43419 | D2241: 43421 | E2241: Second Class | F2241: TG-21310 | G2241: Toby Gnade | H2241: Consumer | I2241: United States | J2241: Los Angeles | K2241: California | L2241: 90049 | M2241: West | N2241: OFF-BI-10003527 | O2241: Office Supplies | P2241: Binders | Q2241: Fellowes PB500 Electric Punch Plastic Comb Binding Machine with Manual Bind | R2241: 1016.792 | S2241: 1 | T2241: 0.2 | U2241: 381.297 | V2241: =IF(M2241=People!$B$2, People!$A$2, IF(M2241=People!$B$3, People!$A$3, IF(M2241=People!$B$4, People!$A$4, IF(M2241=People!$B$5, People!$A$5, 0)))) -> Anna Andreadi | W2241: =IFERROR(VLOOKUP(Orders!$B2241,Returns!$B:$C,2,0),"No") -> No | X2241: =IFERROR((INDEX(Returns!$C$2:$C$801, MATCH(B2241, Returns!$B$2:$B$801, 0))), "No") -> No
A2242: 2241 | B2242: CA-2018-146633 | C2242: 43419 | D2242: 43421 | E2242: Second Class | F2242: TG-21310 | G2242: Toby Gnade | H2242: Consumer | I2242: United States | J2242: Los Angeles | K2242: California | L2242: 90049 | M2242: West | N2242: OFF-BI-10002982 | O2242: Office Supplies | P2242: Binders | Q2242: Avery Self-Adhesive Photo Pockets for Polaroid Photos | R2242: 38.136 | S2242: 7 | T2242: 0.2 | U2242: 13.3476 | V2242: =IF(M2242=People!$B$2, People!$A$2, IF(M2242=People!$B$3, People!$A$3, IF(M2242=People!$B$4, People!$A$4, IF(M2242=People!$B$5, People!$A$5, 0)))) -> Anna Andreadi | W2242: =IFERROR(VLOOKUP(Orders!$B2242,Returns!$B:$C,2,0),"No") -> No | X2242: =IFERROR((INDEX(Returns!$C$2:$C$801, MATCH(B2242, Returns!$B$2:$B$801, 0))), "No") -> No
A2243: 2242 | B2243: US-2018-126893 | C2243: 43430 | D2243: 43435 | E2243: Standard Class | F2243: CT-11995 | G2243: Carol Triggs | H2243: Consumer | I2243: United States | J2243: Philadelphia | K2243: Pennsylvania | L2243: 19134 | M2243: East | N2243: TEC-PH-10004165 | O2243: Technology | P2243: Phones | Q2243: Mitel MiVoice 5330e IP Phone | R2243: 494.982 | S2243: 3 | T2243: 0.4 | U2243: -115.4958 | V2243: =IF(M2243=People!$B$2, People!$A$2, IF(M2243=People!$B$3, People!$A$3, IF(M2243=People!$B$4, People!$A$4, IF(M2243=People!$B$5, People!$A$5, 0)))) -> Chuck Magee | W2243: =IFERROR(VLOOKUP(Orders!$B2243,Returns!$B:$C,2,0),"No") -> No | X2243: =IFERROR((INDEX(Returns!$C$2:$C$801, MATCH(B2243, Returns!$B$2:$B$801, 0))), "No") -> No
A2244: 2243 | B2244: CA-2019-103380 | C2244: 43790 | D2244: 43794 | E2244: Standard Class | F2244: BF-11005 | G2244: Barry Franz | H2244: Home Office | I2244: United States | J2244: Pasadena | K2244: California | L2244: 91104 | M2244: West | N2244: OFF-ST-10003442 | O2244: Office Supplies | P2244: Storage | Q2244: Eldon Portable Mobile Manager | R2244: 56.56 | S2244: 2 | T2244: 0 | U2244: 15.2712 | V2244: =IF(M2244=People!$B$2, People!$A$2, IF(M2244=People!$B$3, People!$A$3, IF(M2244=People!$B$4, People!$A$4, IF(M2244=People!$B$5, People!$A$5, 0)))) -> Anna Andreadi | W2244: =IFERROR(VLOOKUP(Orders!$B2244,Returns!$B:$C,2,0),"No") -> Yes | X2244: =IFERROR((INDEX(Returns!$C$2:$C$801, MATCH(B2244, Returns!$B$2:$B$801, 0))), "No") -> Yes
A2245: 2244 | B2245: CA-2019-103380 | C2245: 43790 | D2245: 43794 | E2245: Standard Class | F2245: BF-11005 | G2245: Barry Franz | H2245: Home Office | I2245: United States | J2245: Pasadena | K2245: California | L2245: 91104 | M2245: West | N2245: OFF-AR-10003856 | O2245: Office Supplies | P2245: Art | Q2245: Newell 344 | R2245: 5.56 | S2245: 2 | T2245: 0 | U2245: 1.4456 | V2245: =IF(M2245=People!$B$2, People!$A$2, IF(M2245=People!$B$3, People!$A$3, IF(M2245=People!$B$4, People!$A$4, IF(M2245=People!$B$5, People!$A$5, 0)))) -> Anna Andreadi | W2245: =IFERROR(VLOOKUP(Orders!$B2245,Returns!$B:$C,2,0),"No") -> Yes | X2245: =IFERROR((INDEX(Returns!$C$2:$C$801, MATCH(B2245, Returns!$B$2:$B$801, 0))), "No") -> Yes
A2246: 2245 | B2246: CA-2019-103380 | C2246: 43790 | D2246: 43794 | E2246: Standard Class | F2246: BF-11005 | G2246: Barry Franz | H2246: Home Office | I2246: United States | J2246: Pasadena | K2246: California | L2246: 91104 | M2246: West | N2246: OFF-FA-10004248 | O2246: Office Supplies | P2246: Fasteners | Q2246: Advantus T-Pin Paper Clips | R2246: 9.02 | S2246: 2 | T2246: 0 | U2246: 3.5178 | V2246: =IF(M2246=People!$B$2, People!$A$2, IF(M2246=People!$B$3, People!$A$3, IF(M2246=People!$B$4, People!$A$4, IF(M2246=People!$B$5, People!$A$5, 0)))) -> Anna Andreadi | W2246: =IFERROR(VLOOKUP(Orders!$B2246,Returns!$B:$C,2,0),"No") -> Yes | X2246: =IFERROR((INDEX(Returns!$C$2:$C$801, MATCH(B2246, Returns!$B$2:$B$801, 0))), "No") -> Yes
A2247: 2246 | B2247: CA-2019-103380 | C2247: 43790 | D2247: 43794 | E2247: Standard Class | F2247: BF-11005 | G2247: Barry Franz | H2247: Home Office | I2247: United States | J2247: Pasadena | K2247: California | L2247: 91104 | M2247: West | N2247: OFF-AP-10001492 | O2247: Office Supplies | P2247: Appliances | Q2247: Acco Six-Outlet Power Strip, 4' Cord Length | R2247: 8.62 | S2247: 1 | T2247: 0 | U2247: 2.2412 | V2247: =IF(M2247=People!$B$2, People!$A$2, IF(M2247=People!$B$3, People!$A$3, IF(M2247=People!$B$4, People!$A$4, IF(M2247=People!$B$5, People!$A$5, 0)))) -> Anna Andreadi | W2247: =IFERROR(VLOOKUP(Orders!$B2247,Returns!$B:$C,2,0),"No") -> Yes | X2247: =IFERROR((INDEX(Returns!$C$2:$C$801, MATCH(B2247, Returns!$B$2:$B$801, 0))), "No") -> Yes
A2248: 2247 | B2248: CA-2019-103380 | C2248: 43790 | D2248: 43794 | E2248: Standard Class | F2248: BF-11005 | G2248: Barry Franz | H2248: Home Office | I2248: United States | J2248: Pasadena | K2248: California | L2248: 91104 | M2248: West | N2248: TEC-PH-10004165 | O2248: Technology | P2248: Phones | Q2248: Mitel MiVoice 5330e IP Phone | R2248: 659.976 | S2248: 3 | T2248: 0.2 | U2248: 49.4982 | V2248: =IF(M2248=People!$B$2, People!$A$2, IF(M2248=People!$B$3, People!$A$3, IF(M2248=People!$B$4, People!$A$4, IF(M2248=People!$B$5, People!$A$5, 0)))) -> Anna Andreadi | W2248: =IFERROR(VLOOKUP(Orders!$B2248,Returns!$B:$C,2,0),"No") -> Yes | X2248: =IFERROR((INDEX(Returns!$C$2:$C$801, MATCH(B2248, Returns!$B$2:$B$801, 0))), "No") -> Yes
... A5275: 5274 | B5275: US-2018-158309 | C5275: 43430 | D5275: 43433 | E5275: First Class | F5275: PA-19060 | G5275: Pete Armstrong | H5275: Home Office | I5275: United States | J5275: Miami | K5275: Florida | L5275: 33142 | M5275: South | N5275: OFF-BI-10000145 | O5275: Office Supplies | P5275: Binders | Q5275: Zipper Ring Binder Pockets | R5275: 3.744 | S5275: 4 | T5275: 0.7 | U5275: -2.6208 | V5275: =IF(M5275=People!$B$2, People!$A$2, IF(M5275=People!$B$3, People!$A$3, IF(M5275=People!$B$4, People!$A$4, IF(M5275=People!$B$5, People!$A$5, 0)))) -> Cassandra Brandow | W5275: =IFERROR(VLOOKUP(Orders!$B5275,Returns!$B:$C,2,0),"No") -> No | X5275: =IFERROR((INDEX(Returns!$C$2:$C$801, MATCH(B5275, Returns!$B$2:$B$801, 0))), "No") -> No
A5276: 5275 | B5276: CA-2017-162887 | C5276: 43046 | D5276: 43048 | E5276: Second Class | F5276: SV-20785 | G5276: Stewart Visinsky | H5276: Consumer | I5276: United States | J5276: Burlington | K5276: Vermont | M5276: East | N5276: FUR-CH-10000595 | O5276: Furniture | P5276: Chairs | Q5276: Safco Contoured Stacking Chairs | R5276: 715.2 | S5276: 3 | T5276: 0 | U5276: 178.8 | V5276: =IF(M5276=People!$B$2, People!$A$2, IF(M5276=People!$B$3, People!$A$3, IF(M5276=People!$B$4, People!$A$4, IF(M5276=People!$B$5, People!$A$5, 0)))) -> Chuck Magee | W5276: =IFERROR(VLOOKUP(Orders!$B5276,Returns!$B:$C,2,0),"No") -> No | X5276: =IFERROR((INDEX(Returns!$C$2:$C$801, MATCH(B5276, Returns!$B$2:$B$801, 0))), "No") -> No
A5277: 5276 | B5277: CA-2019-147333 | C5277: 43813 | D5277: 43819 | E5277: Standard Class | F5277: KL-16555 | G5277: Kelly Lampkin | H5277: Corporate | I5277: United States | J5277: Fayetteville | K5277: Arkansas | L5277: 72701 | M5277: South | N5277: TEC-AC-10004469 | O5277: Technology | P5277: Accessories | Q5277: Microsoft Sculpt Comfort Mouse | R5277: 159.8 | S5277: 4 | T5277: 0 | U5277: 70.312 | V5277: =IF(M5277=People!$B$2, People!$A$2, IF(M5277=People!$B$3, People!$A$3, IF(M5277=People!$B$4, People!$A$4, IF(M5277=People!$B$5, People!$A$5, 0)))) -> Cassandra Brandow | W5277: =IFERROR(VLOOKUP(Orders!$B5277,Returns!$B:$C,2,0),"No") -> No | X5277: =IFERROR((INDEX(Returns!$C$2:$C$801, MATCH(B5277, Returns!$B$2:$B$801, 0))), "No") -> No
A5278: 5277 | B5278: CA-2019-147333 | C5278: 43813 | D5278: 43819 | E5278: Standard Class | F5278: KL-16555 | G5278: Kelly Lampkin | H5278: Corporate | I5278: United States | J5278: Fayetteville | K5278: Arkansas | L5278: 72701 | M5278: South | N5278: TEC-AC-10003038 | O5278: Technology | P5278: Accessories | Q5278: Kingston Digital DataTraveler 16GB USB 2.0 | R5278: 44.75 | S5278: 5 | T5278: 0 | U5278: 8.5025 | V5278: =IF(M5278=People!$B$2, People!$A$2, IF(M5278=People!$B$3, People!$A$3, IF(M5278=People!$B$4, People!$A$4, IF(M5278=People!$B$5, People!$A$5, 0)))) -> Cassandra Brandow | W5278: =IFERROR(VLOOKUP(Orders!$B5278,Returns!$B:$C,2,0),"No") -> No | X5278: =IFERROR((INDEX(Returns!$C$2:$C$801, MATCH(B5278, Returns!$B$2:$B$801, 0))), "No") -> No
A5279: 5278 | B5279: CA-2016-113859 | C5279: 42626 | D5279: 42630 | E5279: Standard Class | F5279: BC-11125 | G5279: Becky Castell | H5279: Home Office | I5279: United States | J5279: Odessa | K5279: Texas | L5279: 79762 | M5279: Central | N5279: FUR-CH-10004698 | O5279: Furniture | P5279: Chairs | Q5279: Padded Folding Chairs, Black, 4/Carton | R5279: 340.116 | S5279: 6 | T5279: 0.3 | U5279: -9.7176 | V5279: =IF(M5279=People!$B$2, People!$A$2, IF(M5279=People!$B$3, People!$A$3, IF(M5279=People!$B$4, People!$A$4, IF(M5279=People!$B$5, People!$A$5, 0)))) -> Kelly Williams | W5279: =IFERROR(VLOOKUP(Orders!$B5279,Returns!$B:$C,2,0),"No") -> No | X5279: =IFERROR((INDEX(Returns!$C$2:$C$801, MATCH(B5279, Returns!$B$2:$B$801, 0))), "No") -> No
A5280: 5279 | B5280: CA-2016-159681 | C5280: 42711 | D5280: 42717 | E5280: Standard Class | F5280: PO-18850 | G5280: Patrick O'Brill | H5280: Consumer | I5280: United States | J5280: Virginia Beach | K5280: Virginia | L5280: 23464 | M5280: South | N5280: OFF-PA-10003641 | O5280: Office Supplies | P5280: Paper | Q5280: Xerox 1909 | R5280: 105.52 | S5280: 4 | T5280: 0 | U5280: 48.5392 | V5280: =IF(M5280=People!$B$2, People!$A$2, IF(M5280=People!$B$3, People!$A$3, IF(M5280=People!$B$4, People!$A$4, IF(M5280=People!$B$5, People!$A$5, 0)))) -> Cassandra Brandow | W5280: =IFERROR(VLOOKUP(Orders!$B5280,Returns!$B:$C,2,0),"No") -> No | X5280: =IFERROR((INDEX(Returns!$C$2:$C$801, MATCH(B5280, Returns!$B$2:$B$801, 0))), "No") -> No
A5281: 5280 | B5281: US-2019-104094 | C5281: 43715 | D5281: 43719 | E5281: Standard Class | F5281: AG-10675 | G5281: Anna Gayman | H5281: Consumer | I5281: United States | J5281: Milwaukee | K5281: Wisconsin | L5281: 53209 | M5281: Central | N5281: TEC-AC-10002134 | O5281: Technology | P5281: Accessories | Q5281: Rosewill 107 Normal Keys USB Wired Standard Keyboard | R5281: 13.48 | S5281: 1 | T5281: 0 | U5281: 1.8872 | V5281: =IF(M5281=People!$B$2, People!$A$2, IF(M5281=People!$B$3, People!$A$3, IF(M5281=People!$B$4, People!$A$4, IF(M5281=People!$B$5, People!$A$5, 0)))) -> Kelly Williams | W5281: =IFERROR(VLOOKUP(Orders!$B5281,Returns!$B:$C,2,0),"No") -> No | X5281: =IFERROR((INDEX(Returns!$C$2:$C$801, MATCH(B5281, Returns!$B$2:$B$801, 0))), "No") -> No
A5282: 5281 | B5282: CA-2019-152709 | C5282: 43745 | D5282: 43750 | E5282: Standard Class | F5282: DB-13210 | G5282: Dean Braden | H5282: Consumer | I5282: United States | J5282: Detroit | K5282: Michigan | L5282: 48234 | M5282: Central | N5282: OFF-ST-10001837 | O5282: Office Supplies | P5282: Storage | Q5282: SAFCO Mobile Desk Side File, Wire Frame | R5282: 85.52 | S5282: 2 | T5282: 0 | U5282: 22.2352 | V5282: =IF(M5282=People!$B$2, People!$A$2, IF(M5282=People!$B$3, People!$A$3, IF(M5282=People!$B$4, People!$A$4, IF(M5282=People!$B$5, People!$A$5, 0)))) -> Kelly Williams | W5282: =IFERROR(VLOOKUP(Orders!$B5282,Returns!$B:$C,2,0),"No") -> No | X5282: =IFERROR((INDEX(Returns!$C$2:$C$801, MATCH(B5282, Returns!$B$2:$B$801, 0))), "No") -> No
A5283: 5282 | B5283: CA-2017-105158 | C5283: 42983 | D5283: 42988 | E5283: Standard Class | F5283: SP-20860 | G5283: Sung Pak | H5283: Corporate | I5283: United States | J5283: Rochester | K5283: Minnesota | L5283: 55901 | M5283: Central | N5283: FUR-FU-10001706 | O5283: Furniture | P5283: Furnishings | Q5283: Longer-Life Soft White Bulbs | R5283: 6.16 | S5283: 2 | T5283: 0 | U5283: 2.9568 | V5283: =IF(M5283=People!$B$2, People!$A$2, IF(M5283=People!$B$3, People!$A$3, IF(M5283=People!$B$4, People!$A$4, IF(M5283=People!$B$5, People!$A$5, 0)))) -> Kelly Williams | W5283: =IFERROR(VLOOKUP(Orders!$B5283,Returns!$B:$C,2,0),"No") -> Yes | X5283: =IFERROR((INDEX(Returns!$C$2:$C$801, MATCH(B5283, Returns!$B$2:$B$801, 0))), "No") -> Yes
A5284: 5283 | B5284: CA-2017-105158 | C5284: 42983 | D5284: 42988 | E5284: Standard Class | F5284: SP-20860 | G5284: Sung Pak | H5284: Corporate | I5284: United States | J5284: Rochester | K5284: Minnesota | L5284: 55901 | M5284: Central | N5284: OFF-PA-10001970 | O5284: Office Supplies | P5284: Paper | Q5284: Xerox 1881 | R5284: 36.84 | S5284: 3 | T5284: 0 | U5284: 17.3148 | V5284: =IF(M5284=People!$B$2, People!$A$2, IF(M5284=People!$B$3, People!$A$3, IF(M5284=People!$B$4, People!$A$4, IF(M5284=People!$B$5, People!$A$5, 0)))) -> Kelly Williams | W5284: =IFERROR(VLOOKUP(Orders!$B5284,Returns!$B:$C,2,0),"No") -> Yes | X5284: =IFERROR((INDEX(Returns!$C$2:$C$801, MATCH(B5284, Returns!$B$2:$B$801, 0))), "No") -> Yes
A5285: 5284 | B5285: CA-2016-133424 | C5285: 42459 | D5285: 42464 | E5285: Standard Class | F5285: Dl-13600 | G5285: Dorris liebe | H5285: Corporate | I5285: United States | J5285: Seattle | K5285: Washington | L5285: 98105 | M5285: West | N5285: OFF-ST-10002957 | O5285: Office Supplies | P5285: Storage | Q5285: Sterilite Show Offs Storage Containers | R5285: 15.84 | S5285: 3 | T5285: 0 | U5285: 0 | V5285: =IF(M5285=People!$B$2, People!$A$2, IF(M5285=People!$B$3, People!$A$3, IF(M5285=People!$B$4, People!$A$4, IF(M5285=People!$B$5, People!$A$5, 0)))) -> Anna Andreadi | W5285: =IFERROR(VLOOKUP(Orders!$B5285,Returns!$B:$C,2,0),"No") -> No | X5285: =IFERROR((INDEX(Returns!$C$2:$C$801, MATCH(B5285, Returns!$B$2:$B$801, 0))), "No") -> No
A5286: 5285 | B5286: CA-2016-133424 | C5286: 42459 | D5286: 42464 | E5286: Standard Class | F5286: Dl-13600 | G5286: Dorris liebe | H5286: Corporate | I5286: United States | J5286: Seattle | K5286: Washington | L5286: 98105 | M5286: West | N5286: OFF-LA-10002312 | O5286: Office Supplies | P5286: Labels | Q5286: Avery 490 | R5286: 44.4 | S5286: 3 | T5286: 0 | U5286: 22.2 | V5286: =IF(M5286=People!$B$2, People!$A$2, IF(M5286=People!$B$3, People!$A$3, IF(M5286=People!$B$4, People!$A$4, IF(M5286=People!$B$5, People!$A$5, 0)))) -> Anna Andreadi | W5286: =IFERROR(VLOOKUP(Orders!$B5286,Returns!$B:$C,2,0),"No") -> No | X5286: =IFERROR((INDEX(Returns!$C$2:$C$801, MATCH(B5286, Returns!$B$2:$B$801, 0))), "No") -> No
A5287: 5286 | B5287: CA-2019-105991 | C5287: 43590 | D5287: 43591 | E5287: First Class | F5287: LH-17020 | G5287: Lisa Hazard | H5287: Consumer | I5287: United States | J5287: Louisville | K5287: Colorado | L5287: 80027 | M5287: West | N5287: OFF-EN-10002600 | O5287: Office Supplies | P5287: Envelopes | Q5287: Redi-Strip #10 Envelopes, 4 1/8 x 9 1/2 | R5287: 21.24 | S5287: 9 | T5287: 0.2 | U5287: 7.434 | V5287: =IF(M5287=People!$B$2, People!$A$2, IF(M5287=People!$B$3, People!$A$3, IF(M5287=People!$B$4, People!$A$4, IF(M5287=People!$B$5, People!$A$5, 0)))) -> Anna Andreadi | W5287: =IFERROR(VLOOKUP(Orders!$B5287,Returns!$B:$C,2,0),"No") -> No | X5287: =IFERROR((INDEX(Returns!$C$2:$C$801, MATCH(B5287, Returns!$B$2:$B$801, 0))), "No") -> No
A5288: 5287 | B5288: CA-2019-105991 | C5288: 43590 | D5288: 43591 | E5288: First Class | F5288: LH-17020 | G5288: Lisa Hazard | H5288: Consumer | I5288: United States | J5288: Louisville | K5288: Colorado | L5288: 80027 | M5288: West | N5288: OFF-BI-10003274 | O5288: Office Supplies | P5288: Binders | Q5288: Avery Durable Slant Ring Binders, No Labels | R5288: 9.552 | S5288: 8 | T5288: 0.7 | U5288: -7.3232 | V5288: =IF(M5288=People!$B$2, People!$A$2, IF(M5288=People!$B$3, People!$A$3, IF(M5288=People!$B$4, People!$A$4, IF(M5288=People!$B$5, People!$A$5, 0)))) -> Anna Andreadi | W5288: =IFERROR(VLOOKUP(Orders!$B5288,Returns!$B:$C,2,0),"No") -> No | X5288: =IFERROR((INDEX(Returns!$C$2:$C$801, MATCH(B5288, Returns!$B$2:$B$801, 0))), "No") -> No
... A8799: 8798 | B8799: CA-2018-106397 | C8799: 43288 | D8799: 43294 | E8799: Standard Class | F8799: MJ-17740 | G8799: Max Jones | H8799: Consumer | I8799: United States | J8799: Orem | K8799: Utah | L8799: 84057 | M8799: West | N8799: OFF-AR-10004602 | O8799: Office Supplies | P8799: Art | Q8799: Boston KS Multi-Size Manual Pencil Sharpener | R8799: 45.98 | S8799: 2 | T8799: 0 | U8799: 12.8744 | V8799: =IF(M8799=People!$B$2, People!$A$2, IF(M8799=People!$B$3, People!$A$3, IF(M8799=People!$B$4, People!$A$4, IF(M8799=People!$B$5, People!$A$5, 0)))) -> Anna Andreadi | W8799: =IFERROR(VLOOKUP(Orders!$B8799,Returns!$B:$C,2,0),"No") -> No | X8799: =IFERROR((INDEX(Returns!$C$2:$C$801, MATCH(B8799, Returns!$B$2:$B$801, 0))), "No") -> No
A8800: 8799 | B8800: US-2018-150140 | C8800: 43196 | D8800: 43200 | E8800: Standard Class | F8800: VM-21685 | G8800: Valerie Mitchum | H8800: Home Office | I8800: United States | J8800: Burlington | K8800: Vermont | M8800: East | N8800: TEC-PH-10002555 | O8800: Technology | P8800: Phones | Q8800: Nortel Meridian M5316 Digital phone | R8800: 1294.75 | S8800: 5 | T8800: 0 | U8800: 336.635 | V8800: =IF(M8800=People!$B$2, People!$A$2, IF(M8800=People!$B$3, People!$A$3, IF(M8800=People!$B$4, People!$A$4, IF(M8800=People!$B$5, People!$A$5, 0)))) -> Chuck Magee | W8800: =IFERROR(VLOOKUP(Orders!$B8800,Returns!$B:$C,2,0),"No") -> No | X8800: =IFERROR((INDEX(Returns!$C$2:$C$801, MATCH(B8800, Returns!$B$2:$B$801, 0))), "No") -> No
A8801: 8800 | B8801: CA-2016-116666 | C8801: 42498 | D8801: 42500 | E8801: First Class | F8801: KT-16480 | G8801: Kean Thornton | H8801: Consumer | I8801: United States | J8801: Philadelphia | K8801: Pennsylvania | L8801: 19134 | M8801: East | N8801: TEC-CO-10001449 | O8801: Technology | P8801: Copiers | Q8801: Hewlett Packard LaserJet 3310 Copier | R8801: 1799.97 | S8801: 5 | T8801: 0.4 | U8801: 239.996 | V8801: =IF(M8801=People!$B$2, People!$A$2, IF(M8801=People!$B$3, People!$A$3, IF(M8801=People!$B$4, People!$A$4, IF(M8801=People!$B$5, People!$A$5, 0)))) -> Chuck Magee | W8801: =IFERROR(VLOOKUP(Orders!$B8801,Returns!$B:$C,2,0),"No") -> No | X8801: =IFERROR((INDEX(Returns!$C$2:$C$801, MATCH(B8801, Returns!$B$2:$B$801, 0))), "No") -> No
A8802: 8801 | B8802: CA-2019-148992 | C8802: 43792 | D8802: 43796 | E8802: Standard Class | F8802: CS-12250 | G8802: Chris Selesnick | H8802: Corporate | I8802: United States | J8802: Chicago | K8802: Illinois | L8802: 60623 | M8802: Central | N8802: OFF-PA-10004285 | O8802: Office Supplies | P8802: Paper | Q8802: Xerox 1959 | R8802: 10.688 | S8802: 2 | T8802: 0.2 | U8802: 3.7408 | V8802: =IF(M8802=People!$B$2, People!$A$2, IF(M8802=People!$B$3, People!$A$3, IF(M8802=People!$B$4, People!$A$4, IF(M8802=People!$B$5, People!$A$5, 0)))) -> Kelly Williams | W8802: =IFERROR(VLOOKUP(Orders!$B8802,Returns!$B:$C,2,0),"No") -> No | X8802: =IFERROR((INDEX(Returns!$C$2:$C$801, MATCH(B8802, Returns!$B$2:$B$801, 0))), "No") -> No
A8803: 8802 | B8803: CA-2018-140935 | C8803: 43414 | D8803: 43416 | E8803: First Class | F8803: AB-10015 | G8803: Aaron Bergman | H8803: Consumer | I8803: United States | J8803: Oklahoma City | K8803: Oklahoma | L8803: 73120 | M8803: Central | N8803: TEC-PH-10000562 | O8803: Technology | P8803: Phones | Q8803: Samsung Convoy 3 | R8803: 221.98 | S8803: 2 | T8803: 0 | U8803: 62.1544 | V8803: =IF(M8803=People!$B$2, People!$A$2, IF(M8803=People!$B$3, People!$A$3, IF(M8803=People!$B$4, People!$A$4, IF(M8803=People!$B$5, People!$A$5, 0)))) -> Kelly Williams | W8803: =IFERROR(VLOOKUP(Orders!$B8803,Returns!$B:$C,2,0),"No") -> No | X8803: =IFERROR((INDEX(Returns!$C$2:$C$801, MATCH(B8803, Returns!$B$2:$B$801, 0))), "No") -> No
A8804: 8803 | B8804: CA-2018-140935 | C8804: 43414 | D8804: 43416 | E8804: First Class | F8804: AB-10015 | G8804: Aaron Bergman | H8804: Consumer | I8804: United States | J8804: Oklahoma City | K8804: Oklahoma | L8804: 73120 | M8804: Central | N8804: FUR-BO-10003966 | O8804: Furniture | P8804: Bookcases | Q8804: Sauder Facets Collection Library, Sky Alder Finish | R8804: 341.96 | S8804: 2 | T8804: 0 | U8804: 54.7136 | V8804: =IF(M8804=People!$B$2, People!$A$2, IF(M8804=People!$B$3, People!$A$3, IF(M8804=People!$B$4, People!$A$4, IF(M8804=People!$B$5, People!$A$5, 0)))) -> Kelly Williams | W8804: =IFERROR(VLOOKUP(Orders!$B8804,Returns!$B:$C,2,0),"No") -> No | X8804: =IFERROR((INDEX(Returns!$C$2:$C$801, MATCH(B8804, Returns!$B$2:$B$801, 0))), "No") -> No
A8805: 8804 | B8805: CA-2016-157644 | C8805: 42735 | D8805: 42736 | E8805: First Class | F8805: AH-10030 | G8805: Aaron Hawkins | H8805: Corporate | I8805: United States | J8805: New York City | K8805: New York | L8805: 10035 | M8805: East | N8805: TEC-AC-10003614 | O8805: Technology | P8805: Accessories | Q8805: Verbatim 25 GB 6x Blu-ray Single Layer Recordable Disc, 10/Pack | R8805: 34.77 | S8805: 3 | T8805: 0 | U8805: 11.4741 | V8805: =IF(M8805=People!$B$2, People!$A$2, IF(M8805=People!$B$3, People!$A$3, IF(M8805=People!$B$4, People!$A$4, IF(M8805=People!$B$5, People!$A$5, 0)))) -> Chuck Magee | W8805: =IFERROR(VLOOKUP(Orders!$B8805,Returns!$B:$C,2,0),"No") -> No | X8805: =IFERROR((INDEX(Returns!$C$2:$C$801, MATCH(B8805, Returns!$B$2:$B$801, 0))), "No") -> No
A8806: 8805 | B8806: CA-2016-157644 | C8806: 42735 | D8806: 42736 | E8806: First Class | F8806: AH-10030 | G8806: Aaron Hawkins | H8806: Corporate | I8806: United States | J8806: New York City | K8806: New York | L8806: 10035 | M8806: East | N8806: OFF-LA-10003148 | O8806: Office Supplies | P8806: Labels | Q8806: Avery 51 | R8806: 18.9 | S8806: 3 | T8806: 0 | U8806: 8.694 | V8806: =IF(M8806=People!$B$2, People!$A$2, IF(M8806=People!$B$3, People!$A$3, IF(M8806=People!$B$4, People!$A$4, IF(M8806=People!$B$5, People!$A$5, 0)))) -> Chuck Magee | W8806: =IFERROR(VLOOKUP(Orders!$B8806,Returns!$B:$C,2,0),"No") -> No | X8806: =IFERROR((INDEX(Returns!$C$2:$C$801, MATCH(B8806, Returns!$B$2:$B$801, 0))), "No") -> No
A8807: 8806 | B8807: US-2019-100398 | C8807: 43696 | D8807: 43700 | E8807: Standard Class | F8807: DO-13435 | G8807: Denny Ordway | H8807: Consumer | I8807: United States | J8807: Salt Lake City | K8807: Utah | L8807: 84106 | M8807: West | N8807: OFF-BI-10002133 | O8807: Office Supplies | P8807: Binders | Q8807: Wilson Jones Elliptical Ring 3 1/2" Capacity Binders, 800 sheets | R8807: 102.72 | S8807: 3 | T8807: 0.2 | U8807: 37.236 | V8807: =IF(M8807=People!$B$2, People!$A$2, IF(M8807=People!$B$3, People!$A$3, IF(M8807=People!$B$4, People!$A$4, IF(M8807=People!$B$5, People!$A$5, 0)))) -> Anna Andreadi | W8807: =IFERROR(VLOOKUP(Orders!$B8807,Returns!$B:$C,2,0),"No") -> No | X8807: =IFERROR((INDEX(Returns!$C$2:$C$801, MATCH(B8807, Returns!$B$2:$B$801, 0))), "No") -> No
A8808: 8807 | B8808: CA-2018-113082 | C8808: 43355 | D8808: 43359 | E8808: Standard Class | F8808: MC-17590 | G8808: Matt Collister | H8808: Corporate | I8808: United States | J8808: Utica | K8808: New York | L8808: 13501 | M8808: East | N8808: FUR-FU-10002813 | O8808: Furniture | P8808: Furnishings | Q8808: DAX Contemporary Wood Frame with Silver Metal Mat, Desktop, 11 x 14 Size | R8808: 40.48 | S8808: 2 | T8808: 0 | U8808: 14.5728 | V8808: =IF(M8808=People!$B$2, People!$A$2, IF(M8808=People!$B$3, People!$A$3, IF(M8808=People!$B$4, People!$A$4, IF(M8808=People!$B$5, People!$A$5, 0)))) -> Chuck Magee | W8808: =IFERROR(VLOOKUP(Orders!$B8808,Returns!$B:$C,2,0),"No") -> No | X8808: =IFERROR((INDEX(Returns!$C$2:$C$801, MATCH(B8808, Returns!$B$2:$B$801, 0))), "No") -> No
A8809: 8808 | B8809: US-2019-110646 | C8809: 43764 | D8809: 43769 | E8809: Standard Class | F8809: JF-15190 | G8809: Jamie Frazer | H8809: Consumer | I8809: United States | J8809: Philadelphia | K8809: Pennsylvania | L8809: 19134 | M8809: East | N8809: OFF-BI-10004330 | O8809: Office Supplies | P8809: Binders | Q8809: GBC Velobind Prepunched Cover Sets, Regency Series | R8809: 33.282 | S8809: 3 | T8809: 0.7 | U8809: -27.735 | V8809: =IF(M8809=People!$B$2, People!$A$2, IF(M8809=People!$B$3, People!$A$3, IF(M8809=People!$B$4, People!$A$4, IF(M8809=People!$B$5, People!$A$5, 0)))) -> Chuck Magee | W8809: =IFERROR(VLOOKUP(Orders!$B8809,Returns!$B:$C,2,0),"No") -> No | X8809: =IFERROR((INDEX(Returns!$C$2:$C$801, MATCH(B8809, Returns!$B$2:$B$801, 0))), "No") -> No
A8810: 8809 | B8810: US-2019-110646 | C8810: 43764 | D8810: 43769 | E8810: Standard Class | F8810: JF-15190 | G8810: Jamie Frazer | H8810: Consumer | I8810: United States | J8810: Philadelphia | K8810: Pennsylvania | L8810: 19134 | M8810: East | N8810: TEC-PH-10002807 | O8810: Technology | P8810: Phones | Q8810: Motorla HX550 Universal Bluetooth Headset | R8810: 118.65 | S8810: 5 | T8810: 0.4 | U8810: 19.775 | V8810: =IF(M8810=People!$B$2, People!$A$2, IF(M8810=People!$B$3, People!$A$3, IF(M8810=People!$B$4, People!$A$4, IF(M8810=People!$B$5, People!$A$5, 0)))) -> Chuck Magee | W8810: =IFERROR(VLOOKUP(Orders!$B8810,Returns!$B:$C,2,0),"No") -> No | X8810: =IFERROR((INDEX(Returns!$C$2:$C$801, MATCH(B8810, Returns!$B$2:$B$801, 0))), "No") -> No
A8811: 8810 | B8811: US-2019-110646 | C8811: 43764 | D8811: 43769 | E8811: Standard Class | F8811: JF-15190 | G8811: Jamie Frazer | H8811: Consumer | I8811: United States | J8811: Philadelphia | K8811: Pennsylvania | L8811: 19134 | M8811: East | N8811: OFF-LA-10001404 | O8811: Office Supplies | P8811: Labels | Q8811: Avery 517 | R8811: 14.76 | S8811: 5 | T8811: 0.2 | U8811: 4.9815 | V8811: =IF(M8811=People!$B$2, People!$A$2, IF(M8811=People!$B$3, People!$A$3, IF(M8811=People!$B$4, People!$A$4, IF(M8811=People!$B$5, People!$A$5, 0)))) -> Chuck Magee | W8811: =IFERROR(VLOOKUP(Orders!$B8811,Returns!$B:$C,2,0),"No") -> No | X8811: =IFERROR((INDEX(Returns!$C$2:$C$801, MATCH(B8811, Returns!$B$2:$B$801, 0))), "No") -> No
A8812: 8811 | B8812: CA-2019-120614 | C8812: 43615 | D8812: 43620 | E8812: Standard Class | F8812: SM-20950 | G8812: Suzanne McNair | H8812: Corporate | I8812: United States | J8812: Los Angeles | K8812: California | L8812: 90004 | M8812: West | N8812: OFF-PA-10004911 | O8812: Office Supplies | P8812: Paper | Q8812: Rediform S.O.S. 1-Up Phone Message Bk, 4-1/4x3-1/16 Bk, 1 Form/Pg, 40 Messages/Bk, 3/Pk | R8812: 37.52 | S8812: 4 | T8812: 0 | U8812: 18.0096 | V8812: =IF(M8812=People!$B$2, People!$A$2, IF(M8812=People!$B$3, People!$A$3, IF(M8812=People!$B$4, People!$A$4, IF(M8812=People!$B$5, People!$A$5, 0)))) -> Anna Andreadi | W8812: =IFERROR(VLOOKUP(Orders!$B8812,Returns!$B:$C,2,0),"No") -> No | X8812: =IFERROR((INDEX(Returns!$C$2:$C$801, MATCH(B8812, Returns!$B$2:$B$801, 0))), "No") -> No
... A9147: 9146 | B9147: CA-2017-126970 | C9147: 42998 | D9147: 43002 | E9147: Standard Class | F9147: TP-21130 | G9147: Theone Pippenger | H9147: Consumer | I9147: United States | J9147: Naperville | K9147: Illinois | L9147: 60540 | M9147: Central | N9147: OFF-BI-10000138 | O9147: Office Supplies | P9147: Binders | Q9147: Acco Translucent Poly Ring Binders | R9147: 2.808 | S9147: 3 | T9147: 0.8 | U9147: -4.4928 | V9147: =IF(M9147=People!$B$2, People!$A$2, IF(M9147=People!$B$3, People!$A$3, IF(M9147=People!$B$4, People!$A$4, IF(M9147=People!$B$5, People!$A$5, 0)))) -> Kelly Williams | W9147: =IFERROR(VLOOKUP(Orders!$B9147,Returns!$B:$C,2,0),"No") -> No | X9147: =IFERROR((INDEX(Returns!$C$2:$C$801, MATCH(B9147, Returns!$B$2:$B$801, 0))), "No") -> No
A9148: 9147 | B9148: US-2018-165505 | C9148: 43123 | D9148: 43127 | E9148: Standard Class | F9148: CB-12535 | G9148: Claudia Bergmann | H9148: Corporate | I9148: United States | J9148: Burlington | K9148: Vermont | M9148: East | N9148: TEC-AC-10002926 | O9148: Technology | P9148: Accessories | Q9148: Logitech Wireless Marathon Mouse M705 | R9148: 99.98 | S9148: 2 | T9148: 0 | U9148: 42.9914 | V9148: =IF(M9148=People!$B$2, People!$A$2, IF(M9148=People!$B$3, People!$A$3, IF(M9148=People!$B$4, People!$A$4, IF(M9148=People!$B$5, People!$A$5, 0)))) -> Chuck Magee | W9148: =IFERROR(VLOOKUP(Orders!$B9148,Returns!$B:$C,2,0),"No") -> No | X9148: =IFERROR((INDEX(Returns!$C$2:$C$801, MATCH(B9148, Returns!$B$2:$B$801, 0))), "No") -> No
A9149: 9148 | B9149: US-2018-165505 | C9149: 43123 | D9149: 43127 | E9149: Standard Class | F9149: CB-12535 | G9149: Claudia Bergmann | H9149: Corporate | I9149: United States | J9149: Burlington | K9149: Vermont | M9149: East | N9149: OFF-AR-10003477 | O9149: Office Supplies | P9149: Art | Q9149: 4009 Highlighters | R9149: 8.04 | S9149: 6 | T9149: 0 | U9149: 2.7336 | V9149: =IF(M9149=People!$B$2, People!$A$2, IF(M9149=People!$B$3, People!$A$3, IF(M9149=People!$B$4, People!$A$4, IF(M9149=People!$B$5, People!$A$5, 0)))) -> Chuck Magee | W9149: =IFERROR(VLOOKUP(Orders!$B9149,Returns!$B:$C,2,0),"No") -> No | X9149: =IFERROR((INDEX(Returns!$C$2:$C$801, MATCH(B9149, Returns!$B$2:$B$801, 0))), "No") -> No
A9150: 9149 | B9150: US-2018-165505 | C9150: 43123 | D9150: 43127 | E9150: Standard Class | F9150: CB-12535 | G9150: Claudia Bergmann | H9150: Corporate | I9150: United States | J9150: Burlington | K9150: Vermont | M9150: East | N9150: OFF-ST-10001526 | O9150: Office Supplies | P9150: Storage | Q9150: Iceberg Mobile Mega Data/Printer Cart | R9150: 1564.29 | S9150: 13 | T9150: 0 | U9150: 406.7154 | V9150: =IF(M9150=People!$B$2, People!$A$2, IF(M9150=People!$B$3, People!$A$3, IF(M9150=People!$B$4, People!$A$4, IF(M9150=People!$B$5, People!$A$5, 0)))) -> Chuck Magee | W9150: =IFERROR(VLOOKUP(Orders!$B9150,Returns!$B:$C,2,0),"No") -> No | X9150: =IFERROR((INDEX(Returns!$C$2:$C$801, MATCH(B9150, Returns!$B$2:$B$801, 0))), "No") -> No
A9151: 9150 | B9151: US-2016-157070 | C9151: 42522 | D9151: 42527 | E9151: Standard Class | F9151: QJ-19255 | G9151: Quincy Jones | H9151: Corporate | I9151: United States | J9151: Detroit | K9151: Michigan | L9151: 48234 | M9151: Central | N9151: OFF-BI-10001765 | O9151: Office Supplies | P9151: Binders | Q9151: Wilson Jones Heavy-Duty Casebound Ring Binders with Metal Hinges | R9151: 138.56 | S9151: 4 | T9151: 0 | U9151: 66.5088 | V9151: =IF(M9151=People!$B$2, People!$A$2, IF(M9151=People!$B$3, People!$A$3, IF(M9151=People!$B$4, People!$A$4, IF(M9151=People!$B$5, People!$A$5, 0)))) -> Kelly Williams | W9151: =IFERROR(VLOOKUP(Orders!$B9151,Returns!$B:$C,2,0),"No") -> No | X9151: =IFERROR((INDEX(Returns!$C$2:$C$801, MATCH(B9151, Returns!$B$2:$B$801, 0))), "No") -> No
A9152: 9151 | B9152: US-2016-157070 | C9152: 42522 | D9152: 42527 | E9152: Standard Class | F9152: QJ-19255 | G9152: Quincy Jones | H9152: Corporate | I9152: United States | J9152: Detroit | K9152: Michigan | L9152: 48234 | M9152: Central | N9152: OFF-AP-10004859 | O9152: Office Supplies | P9152: Appliances | Q9152: Acco 6 Outlet Guardian Premium Surge Suppressor | R9152: 65.52 | S9152: 5 | T9152: 0.1 | U9152: 12.376 | V9152: =IF(M9152=People!$B$2, People!$A$2, IF(M9152=People!$B$3, People!$A$3, IF(M9152=People!$B$4, People!$A$4, IF(M9152=People!$B$5, People!$A$5, 0)))) -> Kelly Williams | W9152: =IFERROR(VLOOKUP(Orders!$B9152,Returns!$B:$C,2,0),"No") -> No | X9152: =IFERROR((INDEX(Returns!$C$2:$C$801, MATCH(B9152, Returns!$B$2:$B$801, 0))), "No") -> No
A9153: 9152 | B9153: US-2017-106873 | C9153: 43002 | D9153: 43007 | E9153: Second Class | F9153: KM-16720 | G9153: Kunst Miller | H9153: Consumer | I9153: United States | J9153: Avondale | K9153: Arizona | L9153: 85323 | M9153: West | N9153: OFF-AR-10003179 | O9153: Office Supplies | P9153: Art | Q9153: Dixon Ticonderoga Core-Lock Colored Pencils | R9153: 14.576 | S9153: 2 | T9153: 0.2 | U9153: 2.3686 | V9153: =IF(M9153=People!$B$2, People!$A$2, IF(M9153=People!$B$3, People!$A$3, IF(M9153=People!$B$4, People!$A$4, IF(M9153=People!$B$5, People!$A$5, 0)))) -> Anna Andreadi | W9153: =IFERROR(VLOOKUP(Orders!$B9153,Returns!$B:$C,2,0),"No") -> No | X9153: =IFERROR((INDEX(Returns!$C$2:$C$801, MATCH(B9153, Returns!$B$2:$B$801, 0))), "No") -> No
A9154: 9153 | B9154: US-2017-106873 | C9154: 43002 | D9154: 43007 | E9154: Second Class | F9154: KM-16720 | G9154: Kunst Miller | H9154: Consumer | I9154: United States | J9154: Avondale | K9154: Arizona | L9154: 85323 | M9154: West | N9154: TEC-AC-10002345 | O9154: Technology | P9154: Accessories | Q9154: HP Standard 104 key PS/2 Keyboard | R9154: 23.2 | S9154: 2 | T9154: 0.2 | U9154: 1.45 | V9154: =IF(M9154=People!$B$2, People!$A$2, IF(M9154=People!$B$3, People!$A$3, IF(M9154=People!$B$4, People!$A$4, IF(M9154=People!$B$5, People!$A$5, 0)))) -> Anna Andreadi | W9154: =IFERROR(VLOOKUP(Orders!$B9154,Returns!$B:$C,2,0),"No") -> No | X9154: =IFERROR((INDEX(Returns!$C$2:$C$801, MATCH(B9154, Returns!$B$2:$B$801, 0))), "No") -> No
A9155: 9154 | B9155: US-2017-106873 | C9155: 43002 | D9155: 43007 | E9155: Second Class | F9155: KM-16720 | G9155: Kunst Miller | H9155: Consumer | I9155: United States | J9155: Avondale | K9155: Arizona | L9155: 85323 | M9155: West | N9155: OFF-AR-10001246 | O9155: Office Supplies | P9155: Art | Q9155: Newell 317 | R9155: 16.464 | S9155: 7 | T9155: 0.2 | U9155: 1.8522 | V9155: =IF(M9155=People!$B$2, People!$A$2, IF(M9155=People!$B$3, People!$A$3, IF(M9155=People!$B$4, People!$A$4, IF(M9155=People!$B$5, People!$A$5, 0)))) -> Anna Andreadi | W9155: =IFERROR(VLOOKUP(Orders!$B9155,Returns!$B:$C,2,0),"No") -> No | X9155: =IFERROR((INDEX(Returns!$C$2:$C$801, MATCH(B9155, Returns!$B$2:$B$801, 0))), "No") -> No
A9156: 9155 | B9156: CA-2018-132990 | C9156: 43313 | D9156: 43315 | E9156: Second Class | F9156: KM-16660 | G9156: Khloe Miller | H9156: Consumer | I9156: United States | J9156: Philadelphia | K9156: Pennsylvania | L9156: 19140 | M9156: East | N9156: FUR-FU-10004864 | O9156: Furniture | P9156: Furnishings | Q9156: Eldon 500 Class Desk Accessories | R9156: 19.312 | S9156: 2 | T9156: 0.2 | U9156: 3.1382 | V9156: =IF(M9156=People!$B$2, People!$A$2, IF(M9156=People!$B$3, People!$A$3, IF(M9156=People!$B$4, People!$A$4, IF(M9156=People!$B$5, People!$A$5, 0)))) -> Chuck Magee | W9156: =IFERROR(VLOOKUP(Orders!$B9156,Returns!$B:$C,2,0),"No") -> No | X9156: =IFERROR((INDEX(Returns!$C$2:$C$801, MATCH(B9156, Returns!$B$2:$B$801, 0))), "No") -> No
A9157: 9156 | B9157: CA-2016-102645 | C9157: 42392 | D9157: 42397 | E9157: Standard Class | F9157: IM-15055 | G9157: Ionia McGrath | H9157: Consumer | I9157: United States | J9157: Las Vegas | K9157: Nevada | L9157: 89115 | M9157: West | N9157: OFF-PA-10001804 | O9157: Office Supplies | P9157: Paper | Q9157: Xerox 195 | R9157: 40.08 | S9157: 6 | T9157: 0 | U9157: 19.2384 | V9157: =IF(M9157=People!$B$2, People!$A$2, IF(M9157=People!$B$3, People!$A$3, IF(M9157=People!$B$4, People!$A$4, IF(M9157=People!$B$5, People!$A$5, 0)))) -> Anna Andreadi | W9157: =IFERROR(VLOOKUP(Orders!$B9157,Returns!$B:$C,2,0),"No") -> No | X9157: =IFERROR((INDEX(Returns!$C$2:$C$801, MATCH(B9157, Returns!$B$2:$B$801, 0))), "No") -> No
A9158: 9157 | B9158: CA-2016-134215 | C9158: 42586 | D9158: 42590 | E9158: Standard Class | F9158: ML-17395 | G9158: Marina Lichtenstein | H9158: Corporate | I9158: United States | J9158: Bangor | K9158: Maine | L9158: 4401 | M9158: East | N9158: OFF-AP-10001271 | O9158: Office Supplies | P9158: Appliances | Q9158: Eureka The Boss Cordless Rechargeable Stick Vac | R9158: 101.96 | S9158: 2 | T9158: 0 | U9158: 27.5292 | V9158: =IF(M9158=People!$B$2, People!$A$2, IF(M9158=People!$B$3, People!$A$3, IF(M9158=People!$B$4, People!$A$4, IF(M9158=People!$B$5, People!$A$5, 0)))) -> Chuck Magee | W9158: =IFERROR(VLOOKUP(Orders!$B9158,Returns!$B:$C,2,0),"No") -> No | X9158: =IFERROR((INDEX(Returns!$C$2:$C$801, MATCH(B9158, Returns!$B$2:$B$801, 0))), "No") -> No
A9159: 9158 | B9159: CA-2016-134215 | C9159: 42586 | D9159: 42590 | E9159: Standard Class | F9159: ML-17395 | G9159: Marina Lichtenstein | H9159: Corporate | I9159: United States | J9159: Bangor | K9159: Maine | L9159: 4401 | M9159: East | N9159: OFF-PA-10004353 | O9159: Office Supplies | P9159: Paper | Q9159: Southworth 25% Cotton Premium Laser Paper and Envelopes | R9159: 259.74 | S9159: 13 | T9159: 0 | U9159: 124.6752 | V9159: =IF(M9159=People!$B$2, People!$A$2, IF(M9159=People!$B$3, People!$A$3, IF(M9159=People!$B$4, People!$A$4, IF(M9159=People!$B$5, People!$A$5, 0)))) -> Chuck Magee | W9159: =IFERROR(VLOOKUP(Orders!$B9159,Returns!$B:$C,2,0),"No") -> No | X9159: =IFERROR((INDEX(Returns!$C$2:$C$801, MATCH(B9159, Returns!$B$2:$B$801, 0))), "No") -> No
A9160: 9159 | B9160: CA-2016-134215 | C9160: 42586 | D9160: 42590 | E9160: Standard Class | F9160: ML-17395 | G9160: Marina Lichtenstein | H9160: Corporate | I9160: United States | J9160: Bangor | K9160: Maine | L9160: 4401 | M9160: East | N9160: TEC-AC-10002473 | O9160: Technology | P9160: Accessories | Q9160: Maxell 4.7GB DVD-R | R9160: 255.42 | S9160: 9 | T9160: 0 | U9160: 104.7222 | V9160: =IF(M9160=People!$B$2, People!$A$2, IF(M9160=People!$B$3, People!$A$3, IF(M9160=People!$B$4, People!$A$4, IF(M9160=People!$B$5, People!$A$5, 0)))) -> Chuck Magee | W9160: =IFERROR(VLOOKUP(Orders!$B9160,Returns!$B:$C,2,0),"No") -> No | X9160: =IFERROR((INDEX(Returns!$C$2:$C$801, MATCH(B9160, Returns!$B$2:$B$801, 0))), "No") -> No
A9161: 9160 | B9161: CA-2018-118934 | C9161: 43321 | D9161: 43326 | E9161: Standard Class | F9161: GH-14410 | G9161: Gary Hansen | H9161: Home Office | I9161: United States | J9161: Hendersonville | K9161: Tennessee | L9161: 37075 | M9161: South | N9161: OFF-BI-10003314 | O9161: Office Supplies | P9161: Binders | Q9161: Tuff Stuff Recycled Round Ring Binders | R9161: 4.338 | S9161: 3 | T9161: 0.7 | U9161: -3.0366 | V9161: =IF(M9161=People!$B$2, People!$A$2, IF(M9161=People!$B$3, People!$A$3, IF(M9161=People!$B$4, People!$A$4, IF(M9161=People!$B$5, People!$A$5, 0)))) -> Cassandra Brandow | W9161: =IFERROR(VLOOKUP(Orders!$B9161,Returns!$B:$C,2,0),"No") -> No | X9161: =IFERROR((INDEX(Returns!$C$2:$C$801, MATCH(B9161, Returns!$B$2:$B$801, 0))), "No") -> No
A9162: 9161 | B9162: CA-2018-118934 | C9162: 43321 | D9162: 43326 | E9162: Standard Class | F9162: GH-14410 | G9162: Gary Hansen | H9162: Home Office | I9162: United States | J9162: Hendersonville | K9162: Tennessee | L9162: 37075 | M9162: South | N9162: OFF-BI-10004465 | O9162: Office Supplies | P9162: Binders | Q9162: Avery Durable Slant Ring Binders | R9162: 11.88 | S9162: 5 | T9162: 0.7 | U9162: -7.92 | V9162: =IF(M9162=People!$B$2, People!$A$2, IF(M9162=People!$B$3, People!$A$3, IF(M9162=People!$B$4, People!$A$4, IF(M9162=People!$B$5, People!$A$5, 0)))) -> Cassandra Brandow | W9162: =IFERROR(VLOOKUP(Orders!$B9162,Returns!$B:$C,2,0),"No") -> No | X9162: =IFERROR((INDEX(Returns!$C$2:$C$801, MATCH(B9162, Returns!$B$2:$B$801, 0))), "No") -> No
... A9387: 9386 | B9387: CA-2019-163097 | C9387: 43704 | D9387: 43708 | E9387: Standard Class | F9387: SF-20200 | G9387: Sarah Foster | H9387: Consumer | I9387: United States | J9387: Mesa | K9387: Arizona | L9387: 85204 | M9387: West | N9387: FUR-FU-10004973 | O9387: Furniture | P9387: Furnishings | Q9387: Flat Face Poster Frame | R9387: 120.576 | S9387: 8 | T9387: 0.2 | U9387: 33.1584 | V9387: =IF(M9387=People!$B$2, People!$A$2, IF(M9387=People!$B$3, People!$A$3, IF(M9387=People!$B$4, People!$A$4, IF(M9387=People!$B$5, People!$A$5, 0)))) -> Anna Andreadi | W9387: =IFERROR(VLOOKUP(Orders!$B9387,Returns!$B:$C,2,0),"No") -> No | X9387: =IFERROR((INDEX(Returns!$C$2:$C$801, MATCH(B9387, Returns!$B$2:$B$801, 0))), "No") -> No
A9388: 9387 | B9388: US-2019-127292 | C9388: 43484 | D9388: 43488 | E9388: Standard Class | F9388: RM-19375 | G9388: Raymond Messe | H9388: Consumer | I9388: United States | J9388: Burlington | K9388: Vermont | M9388: East | N9388: OFF-PA-10000157 | O9388: Office Supplies | P9388: Paper | Q9388: Xerox 191 | R9388: 79.92 | S9388: 4 | T9388: 0 | U9388: 37.5624 | V9388: =IF(M9388=People!$B$2, People!$A$2, IF(M9388=People!$B$3, People!$A$3, IF(M9388=People!$B$4, People!$A$4, IF(M9388=People!$B$5, People!$A$5, 0)))) -> Chuck Magee | W9388: =IFERROR(VLOOKUP(Orders!$B9388,Returns!$B:$C,2,0),"No") -> No | X9388: =IFERROR((INDEX(Returns!$C$2:$C$801, MATCH(B9388, Returns!$B$2:$B$801, 0))), "No") -> No
A9389: 9388 | B9389: US-2019-127292 | C9389: 43484 | D9389: 43488 | E9389: Standard Class | F9389: RM-19375 | G9389: Raymond Messe | H9389: Consumer | I9389: United States | J9389: Burlington | K9389: Vermont | M9389: East | N9389: OFF-PA-10001970 | O9389: Office Supplies | P9389: Paper | Q9389: Xerox 1881 | R9389: 12.28 | S9389: 1 | T9389: 0 | U9389: 5.7716 | V9389: =IF(M9389=People!$B$2, People!$A$2, IF(M9389=People!$B$3, People!$A$3, IF(M9389=People!$B$4, People!$A$4, IF(M9389=People!$B$5, People!$A$5, 0)))) -> Chuck Magee | W9389: =IFERROR(VLOOKUP(Orders!$B9389,Returns!$B:$C,2,0),"No") -> No | X9389: =IFERROR((INDEX(Returns!$C$2:$C$801, MATCH(B9389, Returns!$B$2:$B$801, 0))), "No") -> No
A9390: 9389 | B9390: US-2019-127292 | C9390: 43484 | D9390: 43488 | E9390: Standard Class | F9390: RM-19375 | G9390: Raymond Messe | H9390: Consumer | I9390: United States | J9390: Burlington | K9390: Vermont | M9390: East | N9390: OFF-AP-10000828 | O9390: Office Supplies | P9390: Appliances | Q9390: Avanti 4.4 Cu. Ft. Refrigerator | R9390: 542.94 | S9390: 3 | T9390: 0 | U9390: 152.0232 | V9390: =IF(M9390=People!$B$2, People!$A$2, IF(M9390=People!$B$3, People!$A$3, IF(M9390=People!$B$4, People!$A$4, IF(M9390=People!$B$5, People!$A$5, 0)))) -> Chuck Magee | W9390: =IFERROR(VLOOKUP(Orders!$B9390,Returns!$B:$C,2,0),"No") -> No | X9390: =IFERROR((INDEX(Returns!$C$2:$C$801, MATCH(B9390, Returns!$B$2:$B$801, 0))), "No") -> No
A9391: 9390 | B9391: US-2019-127292 | C9391: 43484 | D9391: 43488 | E9391: Standard Class | F9391: RM-19375 | G9391: Raymond Messe | H9391: Consumer | I9391: United States | J9391: Burlington | K9391: Vermont | M9391: East | N9391: OFF-EN-10001509 | O9391: Office Supplies | P9391: Envelopes | Q9391: Poly String Tie Envelopes | R9391: 2.04 | S9391: 1 | T9391: 0 | U9391: 0.9588 | V9391: =IF(M9391=People!$B$2, People!$A$2, IF(M9391=People!$B$3, People!$A$3, IF(M9391=People!$B$4, People!$A$4, IF(M9391=People!$B$5, People!$A$5, 0)))) -> Chuck Magee | W9391: =IFERROR(VLOOKUP(Orders!$B9391,Returns!$B:$C,2,0),"No") -> No | X9391: =IFERROR((INDEX(Returns!$C$2:$C$801, MATCH(B9391, Returns!$B$2:$B$801, 0))), "No") -> No
A9392: 9391 | B9392: CA-2017-163734 | C9392: 42905 | D9392: 42910 | E9392: Standard Class | F9392: KM-16375 | G9392: Katherine Murray | H9392: Home Office | I9392: United States | J9392: Houston | K9392: Texas | L9392: 77070 | M9392: Central | N9392: OFF-ST-10003692 | O9392: Office Supplies | P9392: Storage | Q9392: Recycled Steel Personal File for Hanging File Folders | R9392: 228.92 | S9392: 5 | T9392: 0.2 | U9392: 14.3075 | V9392: =IF(M9392=People!$B$2, People!$A$2, IF(M9392=People!$B$3, People!$A$3, IF(M9392=People!$B$4, People!$A$4, IF(M9392=People!$B$5, People!$A$5, 0)))) -> Kelly Williams | W9392: =IFERROR(VLOOKUP(Orders!$B9392,Returns!$B:$C,2,0),"No") -> No | X9392: =IFERROR((INDEX(Returns!$C$2:$C$801, MATCH(B9392, Returns!$B$2:$B$801, 0))), "No") -> No
A9393: 9392 | B9393: CA-2019-162474 | C9393: 43537 | D9393: 43540 | E9393: First Class | F9393: FH-14275 | G9393: Frank Hawley | H9393: Corporate | I9393: United States | J9393: Aurora | K9393: Illinois | L9393: 60505 | M9393: Central | N9393: TEC-PH-10004700 | O9393: Technology | P9393: Phones | Q9393: PowerGen Dual USB Car Charger | R9393: 7.992 | S9393: 1 | T9393: 0.2 | U9393: 2.5974 | V9393: =IF(M9393=People!$B$2, People!$A$2, IF(M9393=People!$B$3, People!$A$3, IF(M9393=People!$B$4, People!$A$4, IF(M9393=People!$B$5, People!$A$5, 0)))) -> Kelly Williams | W9393: =IFERROR(VLOOKUP(Orders!$B9393,Returns!$B:$C,2,0),"No") -> No | X9393: =IFERROR((INDEX(Returns!$C$2:$C$801, MATCH(B9393, Returns!$B$2:$B$801, 0))), "No") -> No
A9394: 9393 | B9394: CA-2017-130848 | C9394: 43033 | D9394: 43033 | E9394: Same Day | F9394: DG-13300 | G9394: Deirdre Greer | H9394: Corporate | I9394: United States | J9394: Denver | K9394: Colorado | L9394: 80219 | M9394: West | N9394: FUR-CH-10000422 | O9394: Furniture | P9394: Chairs | Q9394: Global Highback Leather Tilter in Burgundy | R9394: 582.336 | S9394: 8 | T9394: 0.2 | U9394: -29.1168 | V9394: =IF(M9394=People!$B$2, People!$A$2, IF(M9394=People!$B$3, People!$A$3, IF(M9394=People!$B$4, People!$A$4, IF(M9394=People!$B$5, People!$A$5, 0)))) -> Anna Andreadi | W9394: =IFERROR(VLOOKUP(Orders!$B9394,Returns!$B:$C,2,0),"No") -> No | X9394: =IFERROR((INDEX(Returns!$C$2:$C$801, MATCH(B9394, Returns!$B$2:$B$801, 0))), "No") -> No
A9395: 9394 | B9395: CA-2016-125997 | C9395: 42633 | D9395: 42636 | E9395: First Class | F9395: MW-18220 | G9395: Mitch Webber | H9395: Consumer | I9395: United States | J9395: New York City | K9395: New York | L9395: 10011 | M9395: East | N9395: TEC-PH-10003484 | O9395: Technology | P9395: Phones | Q9395: Ooma Telo VoIP Home Phone System | R9395: 629.95 | S9395: 5 | T9395: 0 | U9395: 157.4875 | V9395: =IF(M9395=People!$B$2, People!$A$2, IF(M9395=People!$B$3, People!$A$3, IF(M9395=People!$B$4, People!$A$4, IF(M9395=People!$B$5, People!$A$5, 0)))) -> Chuck Magee | W9395: =IFERROR(VLOOKUP(Orders!$B9395,Returns!$B:$C,2,0),"No") -> No | X9395: =IFERROR((INDEX(Returns!$C$2:$C$801, MATCH(B9395, Returns!$B$2:$B$801, 0))), "No") -> No
A9396: 9395 | B9396: CA-2016-125997 | C9396: 42633 | D9396: 42636 | E9396: First Class | F9396: MW-18220 | G9396: Mitch Webber | H9396: Consumer | I9396: United States | J9396: New York City | K9396: New York | L9396: 10011 | M9396: East | N9396: FUR-CH-10001394 | O9396: Furniture | P9396: Chairs | Q9396: Global Leather Executive Chair | R9396: 631.782 | S9396: 2 | T9396: 0.1 | U9396: 140.396 | V9396: =IF(M9396=People!$B$2, People!$A$2, IF(M9396=People!$B$3, People!$A$3, IF(M9396=People!$B$4, People!$A$4, IF(M9396=People!$B$5, People!$A$5, 0)))) -> Chuck Magee | W9396: =IFERROR(VLOOKUP(Orders!$B9396,Returns!$B:$C,2,0),"No") -> No | X9396: =IFERROR((INDEX(Returns!$C$2:$C$801, MATCH(B9396, Returns!$B$2:$B$801, 0))), "No") -> No
A9397: 9396 | B9397: CA-2016-125997 | C9397: 42633 | D9397: 42636 | E9397: First Class | F9397: MW-18220 | G9397: Mitch Webber | H9397: Consumer | I9397: United States | J9397: New York City | K9397: New York | L9397: 10011 | M9397: East | N9397: FUR-BO-10002213 | O9397: Furniture | P9397: Bookcases | Q9397: DMI Eclipse Executive Suite Bookcases | R9397: 801.568 | S9397: 2 | T9397: 0.2 | U9397: -10.0196 | V9397: =IF(M9397=People!$B$2, People!$A$2, IF(M9397=People!$B$3, People!$A$3, IF(M9397=People!$B$4, People!$A$4, IF(M9397=People!$B$5, People!$A$5, 0)))) -> Chuck Magee | W9397: =IFERROR(VLOOKUP(Orders!$B9397,Returns!$B:$C,2,0),"No") -> No | X9397: =IFERROR((INDEX(Returns!$C$2:$C$801, MATCH(B9397, Returns!$B$2:$B$801, 0))), "No") -> No
A9398: 9397 | B9398: CA-2016-125997 | C9398: 42633 | D9398: 42636 | E9398: First Class | F9398: MW-18220 | G9398: Mitch Webber | H9398: Consumer | I9398: United States | J9398: New York City | K9398: New York | L9398: 10011 | M9398: East | N9398: OFF-LA-10002762 | O9398: Office Supplies | P9398: Labels | Q9398: Avery 485 | R9398: 75.18 | S9398: 6 | T9398: 0 | U9398: 35.3346 | V9398: =IF(M9398=People!$B$2, People!$A$2, IF(M9398=People!$B$3, People!$A$3, IF(M9398=People!$B$4, People!$A$4, IF(M9398=People!$B$5, People!$A$5, 0)))) -> Chuck Magee | W9398: =IFERROR(VLOOKUP(Orders!$B9398,Returns!$B:$C,2,0),"No") -> No | X9398: =IFERROR((INDEX(Returns!$C$2:$C$801, MATCH(B9398, Returns!$B$2:$B$801, 0))), "No") -> No
A9399: 9398 | B9399: CA-2016-125997 | C9399: 42633 | D9399: 42636 | E9399: First Class | F9399: MW-18220 | G9399: Mitch Webber | H9399: Consumer | I9399: United States | J9399: New York City | K9399: New York | L9399: 10011 | M9399: East | N9399: OFF-AP-10003842 | O9399: Office Supplies | P9399: Appliances | Q9399: Euro-Pro Shark Turbo Vacuum | R9399: 30.98 | S9399: 1 | T9399: 0 | U9399: 8.0548 | V9399: =IF(M9399=People!$B$2, People!$A$2, IF(M9399=People!$B$3, People!$A$3, IF(M9399=People!$B$4, People!$A$4, IF(M9399=People!$B$5, People!$A$5, 0)))) -> Chuck Magee | W9399: =IFERROR(VLOOKUP(Orders!$B9399,Returns!$B:$C,2,0),"No") -> No | X9399: =IFERROR((INDEX(Returns!$C$2:$C$801, MATCH(B9399, Returns!$B$2:$B$801, 0))), "No") -> No
A9400: 9399 | B9400: CA-2016-125997 | C9400: 42633 | D9400: 42636 | E9400: First Class | F9400: MW-18220 | G9400: Mitch Webber | H9400: Consumer | I9400: United States | J9400: New York City | K9400: New York | L9400: 10011 | M9400: East | N9400: TEC-PH-10003072 | O9400: Technology | P9400: Phones | Q9400: Panasonic KX-TG9541B DECT 6.0 Digital 2-Line Expandable Cordless Phone With Digital Answering System | R9400: 1349.91 | S9400: 9 | T9400: 0 | U9400: 661.4559 | V9400: =IF(M9400=People!$B$2, People!$A$2, IF(M9400=People!$B$3, People!$A$3, IF(M9400=People!$B$4, People!$A$4, IF(M9400=People!$B$5, People!$A$5, 0)))) -> Chuck Magee | W9400: =IFERROR(VLOOKUP(Orders!$B9400,Returns!$B:$C,2,0),"No") -> No | X9400: =IFERROR((INDEX(Returns!$C$2:$C$801, MATCH(B9400, Returns!$B$2:$B$801, 0))), "No") -> No
A9401: 9400 | B9401: CA-2018-103128 | C9401: 43415 | D9401: 43419 | E9401: Standard Class | F9401: SC-20845 | G9401: Sung Chung | H9401: Consumer | I9401: United States | J9401: Arlington Heights | K9401: Illinois | L9401: 60004 | M9401: Central | N9401: OFF-AR-10003394 | O9401: Office Supplies | P9401: Art | Q9401: Newell 332 | R9401: 14.112 | S9401: 6 | T9401: 0.2 | U9401: 1.2348 | V9401: =IF(M9401=People!$B$2, People!$A$2, IF(M9401=People!$B$3, People!$A$3, IF(M9401=People!$B$4, People!$A$4, IF(M9401=People!$B$5, People!$A$5, 0)))) -> Kelly Williams | W9401: =IFERROR(VLOOKUP(Orders!$B9401,Returns!$B:$C,2,0),"No") -> No | X9401: =IFERROR((INDEX(Returns!$C$2:$C$801, MATCH(B9401, Returns!$B$2:$B$801, 0))), "No") -> No
A9402: 9401 | B9402: CA-2017-167696 | C9402: 42994 | D9402: 42999 | E9402: Standard Class | F9402: BD-11500 | G9402: Bradley Drucker | H9402: Consumer | I9402: United States | J9402: Newport News | K9402: Virginia | L9402: 23602 | M9402: South | N9402: OFF-EN-10001539 | O9402: Office Supplies | P9402: Envelopes | Q9402: Staple envelope | R9402: 31.12 | S9402: 4 | T9402: 0 | U9402: 14.6264 | V9402: =IF(M9402=People!$B$2, People!$A$2, IF(M9402=People!$B$3, People!$A$3, IF(M9402=People!$B$4, People!$A$4, IF(M9402=People!$B$5, People!$A$5, 0)))) -> Cassandra Brandow | W9402: =IFERROR(VLOOKUP(Orders!$B9402,Returns!$B:$C,2,0),"No") -> No | X9402: =IFERROR((INDEX(Returns!$C$2:$C$801, MATCH(B9402, Returns!$B$2:$B$801, 0))), "No") -> No
A9403: 9402 | B9403: CA-2016-159814 | C9403: 42545 | D9403: 42549 | E9403: Standard Class | F9403: LP-17080 | G9403: Liz Pelletier | H9403: Consumer | I9403: United States | J9403: Tucson | K9403: Arizona | L9403: 85705 | M9403: West | N9403: FUR-FU-10001731 | O9403: Furniture | P9403: Furnishings | Q9403: Acrylic Self-Standing Desk Frames | R9403: 4.272 | S9403: 2 | T9403: 0.2 | U9403: 0.9612 | V9403: =IF(M9403=People!$B$2, People!$A$2, IF(M9403=People!$B$3, People!$A$3, IF(M9403=People!$B$4, People!$A$4, IF(M9403=People!$B$5, People!$A$5, 0)))) -> Anna Andreadi | W9403: =IFERROR(VLOOKUP(Orders!$B9403,Returns!$B:$C,2,0),"No") -> No | X9403: =IFERROR((INDEX(Returns!$C$2:$C$801, MATCH(B9403, Returns!$B$2:$B$801, 0))), "No") -> No
... A9742: 9741 | B9742: CA-2019-129294 | C9742: 43540 | D9742: 43545 | E9742: Standard Class | F9742: KD-16615 | G9742: Ken Dana | H9742: Corporate | I9742: United States | J9742: Los Angeles | K9742: California | L9742: 90032 | M9742: West | N9742: OFF-AP-10001154 | O9742: Office Supplies | P9742: Appliances | Q9742: Bionaire Personal Warm Mist Humidifier/Vaporizer | R9742: 140.67 | S9742: 3 | T9742: 0 | U9742: 54.8613 | V9742: =IF(M9742=People!$B$2, People!$A$2, IF(M9742=People!$B$3, People!$A$3, IF(M9742=People!$B$4, People!$A$4, IF(M9742=People!$B$5, People!$A$5, 0)))) -> Anna Andreadi | W9742: =IFERROR(VLOOKUP(Orders!$B9742,Returns!$B:$C,2,0),"No") -> No | X9742: =IFERROR((INDEX(Returns!$C$2:$C$801, MATCH(B9742, Returns!$B$2:$B$801, 0))), "No") -> No
A9743: 9742 | B9743: CA-2017-117086 | C9743: 43047 | D9743: 43051 | E9743: Standard Class | F9743: QJ-19255 | G9743: Quincy Jones | H9743: Corporate | I9743: United States | J9743: Burlington | K9743: Vermont | M9743: East | N9743: FUR-BO-10004834 | O9743: Furniture | P9743: Bookcases | Q9743: Riverside Palais Royal Lawyers Bookcase, Royale Cherry Finish | R9743: 4404.9 | S9743: 5 | T9743: 0 | U9743: 1013.127 | V9743: =IF(M9743=People!$B$2, People!$A$2, IF(M9743=People!$B$3, People!$A$3, IF(M9743=People!$B$4, People!$A$4, IF(M9743=People!$B$5, People!$A$5, 0)))) -> Chuck Magee | W9743: =IFERROR(VLOOKUP(Orders!$B9743,Returns!$B:$C,2,0),"No") -> No | X9743: =IFERROR((INDEX(Returns!$C$2:$C$801, MATCH(B9743, Returns!$B$2:$B$801, 0))), "No") -> No
A9744: 9743 | B9744: CA-2019-131303 | C9744: 43797 | D9744: 43801 | E9744: Standard Class | F9744: EP-13915 | G9744: Emily Phan | H9744: Consumer | I9744: United States | J9744: San Diego | K9744: California | L9744: 92037 | M9744: West | N9744: OFF-LA-10001074 | O9744: Office Supplies | P9744: Labels | Q9744: Round Specialty Laser Printer Labels | R9744: 62.65 | S9744: 5 | T9744: 0 | U9744: 29.4455 | V9744: =IF(M9744=People!$B$2, People!$A$2, IF(M9744=People!$B$3, People!$A$3, IF(M9744=People!$B$4, People!$A$4, IF(M9744=People!$B$5, People!$A$5, 0)))) -> Anna Andreadi | W9744: =IFERROR(VLOOKUP(Orders!$B9744,Returns!$B:$C,2,0),"No") -> No | X9744: =IFERROR((INDEX(Returns!$C$2:$C$801, MATCH(B9744, Returns!$B$2:$B$801, 0))), "No") -> No
A9745: 9744 | B9745: CA-2018-137127 | C9745: 43267 | D9745: 43273 | E9745: Standard Class | F9745: JJ-15445 | G9745: Jennifer Jackson | H9745: Consumer | I9745: United States | J9745: Newark | K9745: Delaware | L9745: 19711 | M9745: East | N9745: OFF-LA-10001641 | O9745: Office Supplies | P9745: Labels | Q9745: Avery 518 | R9745: 9.45 | S9745: 3 | T9745: 0 | U9745: 4.536 | V9745: =IF(M9745=People!$B$2, People!$A$2, IF(M9745=People!$B$3, People!$A$3, IF(M9745=People!$B$4, People!$A$4, IF(M9745=People!$B$5, People!$A$5, 0)))) -> Chuck Magee | W9745: =IFERROR(VLOOKUP(Orders!$B9745,Returns!$B:$C,2,0),"No") -> No | X9745: =IFERROR((INDEX(Returns!$C$2:$C$801, MATCH(B9745, Returns!$B$2:$B$801, 0))), "No") -> No
A9746: 9745 | B9746: CA-2019-141782 | C9746: 43486 | D9746: 43490 | E9746: Standard Class | F9746: BE-11410 | G9746: Bobby Elias | H9746: Consumer | I9746: United States | J9746: Aurora | K9746: Illinois | L9746: 60505 | M9746: Central | N9746: OFF-EN-10002230 | O9746: Office Supplies | P9746: Envelopes | Q9746: Airmail Envelopes | R9746: 268.576 | S9746: 4 | T9746: 0.2 | U9746: 90.6444 | V9746: =IF(M9746=People!$B$2, People!$A$2, IF(M9746=People!$B$3, People!$A$3, IF(M9746=People!$B$4, People!$A$4, IF(M9746=People!$B$5, People!$A$5, 0)))) -> Kelly Williams | W9746: =IFERROR(VLOOKUP(Orders!$B9746,Returns!$B:$C,2,0),"No") -> No | X9746: =IFERROR((INDEX(Returns!$C$2:$C$801, MATCH(B9746, Returns!$B$2:$B$801, 0))), "No") -> No
A9747: 9746 | B9747: CA-2019-137505 | C9747: 43793 | D9747: 43793 | E9747: Same Day | F9747: BP-11290 | G9747: Beth Paige | H9747: Consumer | I9747: United States | J9747: Los Angeles | K9747: California | L9747: 90008 | M9747: West | N9747: FUR-TA-10000617 | O9747: Furniture | P9747: Tables | Q9747: Hon Practical Foundations 30 x 60 Training Table, Light Gray/Charcoal | R9747: 364.08 | S9747: 2 | T9747: 0.2 | U9747: 9.102 | V9747: =IF(M9747=People!$B$2, People!$A$2, IF(M9747=People!$B$3, People!$A$3, IF(M9747=People!$B$4, People!$A$4, IF(M9747=People!$B$5, People!$A$5, 0)))) -> Anna Andreadi | W9747: =IFERROR(VLOOKUP(Orders!$B9747,Returns!$B:$C,2,0),"No") -> No | X9747: =IFERROR((INDEX(Returns!$C$2:$C$801, MATCH(B9747, Returns!$B$2:$B$801, 0))), "No") -> No
A9748: 9747 | B9748: CA-2019-137505 | C9748: 43793 | D9748: 43793 | E9748: Same Day | F9748: BP-11290 | G9748: Beth Paige | H9748: Consumer | I9748: United States | J9748: Los Angeles | K9748: California | L9748: 90008 | M9748: West | N9748: FUR-TA-10001676 | O9748: Furniture | P9748: Tables | Q9748: Hon 61000 Series Interactive Training Tables | R9748: 71.088 | S9748: 2 | T9748: 0.2 | U9748: -1.7772 | V9748: =IF(M9748=People!$B$2, People!$A$2, IF(M9748=People!$B$3, People!$A$3, IF(M9748=People!$B$4, People!$A$4, IF(M9748=People!$B$5, People!$A$5, 0)))) -> Anna Andreadi | W9748: =IFERROR(VLOOKUP(Orders!$B9748,Returns!$B:$C,2,0),"No") -> No | X9748: =IFERROR((INDEX(Returns!$C$2:$C$801, MATCH(B9748, Returns!$B$2:$B$801, 0))), "No") -> No
A9749: 9748 | B9749: US-2016-140914 | C9749: 42685 | D9749: 42689 | E9749: Standard Class | F9749: BH-11710 | G9749: Brosina Hoffman | H9749: Consumer | I9749: United States | J9749: Chicago | K9749: Illinois | L9749: 60653 | M9749: Central | N9749: FUR-FU-10000175 | O9749: Furniture | P9749: Furnishings | Q9749: DAX Wood Document Frame. | R9749: 10.984 | S9749: 2 | T9749: 0.6 | U9749: -7.9634 | V9749: =IF(M9749=People!$B$2, People!$A$2, IF(M9749=People!$B$3, People!$A$3, IF(M9749=People!$B$4, People!$A$4, IF(M9749=People!$B$5, People!$A$5, 0)))) -> Kelly Williams | W9749: =IFERROR(VLOOKUP(Orders!$B9749,Returns!$B:$C,2,0),"No") -> No | X9749: =IFERROR((INDEX(Returns!$C$2:$C$801, MATCH(B9749, Returns!$B$2:$B$801, 0))), "No") -> No
A9750: 9749 | B9750: US-2016-140914 | C9750: 42685 | D9750: 42689 | E9750: Standard Class | F9750: BH-11710 | G9750: Brosina Hoffman | H9750: Consumer | I9750: United States | J9750: Chicago | K9750: Illinois | L9750: 60653 | M9750: Central | N9750: FUR-CH-10003379 | O9750: Furniture | P9750: Chairs | Q9750: Global Commerce Series High-Back Swivel/Tilt Chairs | R9750: 797.944 | S9750: 4 | T9750: 0.3 | U9750: -56.996 | V9750: =IF(M9750=People!$B$2, People!$A$2, IF(M9750=People!$B$3, People!$A$3, IF(M9750=People!$B$4, People!$A$4, IF(M9750=People!$B$5, People!$A$5, 0)))) -> Kelly Williams | W9750: =IFERROR(VLOOKUP(Orders!$B9750,Returns!$B:$C,2,0),"No") -> No | X9750: =IFERROR((INDEX(Returns!$C$2:$C$801, MATCH(B9750, Returns!$B$2:$B$801, 0))), "No") -> No
A9751: 9750 | B9751: CA-2018-158358 | C9751: 43163 | D9751: 43167 | E9751: Standard Class | F9751: EM-13810 | G9751: Eleni McCrary | H9751: Corporate | I9751: United States | J9751: Dover | K9751: New Hampshire | L9751: 3820 | M9751: East | N9751: TEC-AC-10002567 | O9751: Technology | P9751: Accessories | Q9751: Logitech G602 Wireless Gaming Mouse | R9751: 159.98 | S9751: 2 | T9751: 0 | U9751: 57.5928 | V9751: =IF(M9751=People!$B$2, People!$A$2, IF(M9751=People!$B$3, People!$A$3, IF(M9751=People!$B$4, People!$A$4, IF(M9751=People!$B$5, People!$A$5, 0)))) -> Chuck Magee | W9751: =IFERROR(VLOOKUP(Orders!$B9751,Returns!$B:$C,2,0),"No") -> No | X9751: =IFERROR((INDEX(Returns!$C$2:$C$801, MATCH(B9751, Returns!$B$2:$B$801, 0))), "No") -> No
A9752: 9751 | B9752: CA-2018-113390 | C9752: 43384 | D9752: 43388 | E9752: Standard Class | F9752: EP-13915 | G9752: Emily Phan | H9752: Consumer | I9752: United States | J9752: Chicago | K9752: Illinois | L9752: 60610 | M9752: Central | N9752: OFF-AR-10003183 | O9752: Office Supplies | P9752: Art | Q9752: Avery Fluorescent Highlighter Four-Color Set | R9752: 5.344 | S9752: 2 | T9752: 0.2 | U9752: 0.668 | V9752: =IF(M9752=People!$B$2, People!$A$2, IF(M9752=People!$B$3, People!$A$3, IF(M9752=People!$B$4, People!$A$4, IF(M9752=People!$B$5, People!$A$5, 0)))) -> Kelly Williams | W9752: =IFERROR(VLOOKUP(Orders!$B9752,Returns!$B:$C,2,0),"No") -> No | X9752: =IFERROR((INDEX(Returns!$C$2:$C$801, MATCH(B9752, Returns!$B$2:$B$801, 0))), "No") -> No
A9753: 9752 | B9753: CA-2018-113390 | C9753: 43384 | D9753: 43388 | E9753: Standard Class | F9753: EP-13915 | G9753: Emily Phan | H9753: Consumer | I9753: United States | J9753: Chicago | K9753: Illinois | L9753: 60610 | M9753: Central | N9753: OFF-AR-10001446 | O9753: Office Supplies | P9753: Art | Q9753: Newell 309 | R9753: 27.72 | S9753: 3 | T9753: 0.2 | U9753: 3.465 | V9753: =IF(M9753=People!$B$2, People!$A$2, IF(M9753=People!$B$3, People!$A$3, IF(M9753=People!$B$4, People!$A$4, IF(M9753=People!$B$5, People!$A$5, 0)))) -> Kelly Williams | W9753: =IFERROR(VLOOKUP(Orders!$B9753,Returns!$B:$C,2,0),"No") -> No | X9753: =IFERROR((INDEX(Returns!$C$2:$C$801, MATCH(B9753, Returns!$B$2:$B$801, 0))), "No") -> No
...

Sheet People
A1: Person | B1: Region
A2: Anna Andreadi | B2: West
A3: Chuck Magee | B3: East
A4: Kelly Williams | B4: Central
A5: Cassandra Brandow | B5: South

Sheet Returns
B1: Order ID | C1: Returned
B2: CA-2016-100762 | C2: Yes
B3: CA-2016-100762 | C3: Yes
B4: CA-2016-100762 | C4: Yes
B5: CA-2016-100762 | C5: Yes
B6: CA-2016-100867 | C6: Yes
B7: CA-2016-102652 | C7: Yes
B8: CA-2016-102652 | C8: Yes
B9: CA-2016-102652 | C9: Yes
B10: CA-2016-102652 | C10: Yes
B11: CA-2016-103373 | C11: Yes
B12: CA-2016-103744 | C12: Yes
... B801: US-2019-155999 | C801: Yes

Sheet Динамика доходов и прибыли
B3: Данные
A4: Названия строк | B4: Сумма по полю Sales | C4: Сумма по полю Profit
A5: 2016
A6: янв | B6: 14236.895 | C6: 2450.1907
A7: фев | B7: 4519.892 | C7: 862.3084
A8: мар | B8: 55691.009 | C8: 498.7299
A9: апр | B9: 28295.345 | C9: 3488.8352
A10: май | B10: 23648.287 | C10: 2738.7096
A11: июн | B11: 34595.128 | C11: 4976.5244
A12: июл | B12: 33946.393 | C12: -841.4826
A13: авг | B13: 27909.468 | C13: 5318.105
A14: сен | B14: 81777.351 | C14: 8328.0994
A15: окт | B15: 31453.393 | C15: 3448.2573
A16: ноя | B16: 78628.717 | C16: 9292.1269
A17: дек | B17: 69545.62 | C17: 8983.5699
A18: 2017
A19: янв | B19: 18174.076 | C19: -3281.007
A20: фев | B20: 11951.411 | C20: 2813.8508
A21: мар | B21: 38726.252 | C21: 9732.0978
A22: апр | B22: 34195.208 | C22: 4187.4962
A23: май | B23: 30131.686 | C23: 4667.869
A24: июн | B24: 24797.292 | C24: 3335.5572
A25: июл | B25: 28765.325 | C25: 3288.6483
A26: авг | B26: 36898.332 | C26: 5355.8084
A27: сен | B27: 64595.918 | C27: 8209.1627
A28: окт | B28: 31404.924 | C28: 2817.366
A29: ноя | B29: 75972.564 | C29: 12474.788
A30: дек | B30: 74919.521 | C30: 8016.9659
A31: 2018
A32: янв | B32: 18542.491 | C32: 2824.8233
A33: фев | B33: 22978.815 | C33: 5004.5795
A34: мар | B34: 51715.875 | C34: 3611.968
A35: апр | B35: 38750.039 | C35: 2977.8149
A36: май | B36: 56987.728 | C36: 8662.1464
A37: июн | B37: 40344.534 | C37: 4750.3781
A38: июл | B38: 39261.963 | C38: 4432.8779
A39: авг | B39: 31115.374 | C39: 2062.0693
A40: сен | B40: 73410.025 | C40: 9328.6576
A41: окт | B41: 59687.745 | C41: 16243.143
A42: ноя | B42: 79411.966 | C42: 4011.4075
A43: дек | B43: 96999.043 | C43: 17885.309
A44: 2019
A45: янв | B45: 43971.374 | C45: 7140.4391
A46: фев | B46: 20301.133 | C46: 1613.872
A47: мар | B47: 58872.353 | C47: 14751.891
A48: апр | B48: 36521.536 | C48: 933.29
A49: май | B49: 44261.11 | C49: 6342.5828
A50: июн | B50: 52981.726 | C50: 8223.3357
A51: июл | B51: 45264.416 | C51: 6952.6212
A52: авг | B52: 63120.888 | C52: 9040.9557
A53: сен | B53: 87866.652 | C53: 10991.556
A54: окт | B54: 77776.923 | C54: 9275.2755
A55: ноя | B55: 118447.83 | C55: 9690.1037
A56: дек | B56: 83829.319 | C56: 8483.3468
A57: Общий итог | B57: 2297200.9 | C57: 286397.02

Sheet Категории товаров
B1: Данные
A2: Названия строк | B2: Сумма по полю Sales | C2: Сумма по полю Profit
A3: Furniture | B3: 741999.8 | C3: 18451.273
A4: Office Supplies | B4: 719047.03 | C4: 122490.8
A5: Technology | B5: 836154.03 | C5: 145454.95
A6: Общий итог | B6: 2297200.9 | C6: 286397.02

Sheet Региональные менеджеры
B3: Данные
A4: Person | B4: Сумма по полю Sales | C4: Сумма по полю Profit
A5: Cassandra Brandow | B5: 391721.91 | C5: 46749.43
A6: Kelly Williams | B6: 501239.89 | C6: 39706.362
A7: Chuck Magee | B7: 678781.24 | C7: 91522.78
A8: Anna Andreadi | B8: 725457.82 | C8: 108418.45
A9: Общий итог | B9: 2297200.9 | C9: 286397.02

Sheet Сегменты
B3: Данные
A4: Segment | B4: Сумма по полю Sales | C4: Сумма по полю Profit
A5: Home Office | B5: 429653.15 | C5: 60298.679
A6: Corporate | B6: 706146.37 | C6: 91979.134
A7: Consumer | B7: 1161401.3 | C7: 134119.21
A8: Общий итог | B8: 2297200.9 | C8: 286397.02

Sheet Динамика сегментов
A3: Сумма по полю Sales | B3: Названия столбцов
A4: Названия строк | B4: Consumer | C4: Corporate | D4: Home Office | E4: Общий итог
A5: 2016 | B5: 266096.81 | C5: 128434.87 | D5: 89715.812 | E5: 484247.5
A6: 2017 | B6: 266535.93 | C6: 128757.31 | D6: 75239.269 | E6: 470532.51
A7: 2018 | B7: 296863.9 | C7: 207106.36 | D7: 105235.34 | E7: 609205.6
A8: 2019 | B8: 331904.7 | C8: 241847.82 | D8: 159462.73 | E8: 733215.26
A9: Общий итог | B9: 1161401.3 | C9: 706146.37 | D9: 429653.15 | E9: 2297200.9

Sheet Основные показатели
C3: Данные
A4: Годы | B4: Order Date | C4: Сумма по полю Sales | D4: Сумма по полю Profit | E4: Сумма по полю Profit ratio | F4: Среднее по полю Discount
A5: 2016 | B5: янв | C5: 14236.895 | D5: 2450.1907 | E5: 0.17210148 | F5: 0.12658228
B6: фев | C6: 4519.892 | D6: 862.3084 | E6: 0.19078075 | F6: 0.17608696
B7: мар | C7: 55691.009 | D7: 498.7299 | E7: 0.0089553037 | F7: 0.16751592
B8: апр | C8: 28295.345 | D8: 3488.8352 | E8: 0.12330068 | F8: 0.11
B9: май | C9: 23648.287 | D9: 2738.7096 | E9: 0.11581006 | F9: 0.15532787
B10: июн | C10: 34595.128 | D10: 4976.5244 | E10: 0.14385044 | F10: 0.172
B11: июл | C11: 33946.393 | D11: -841.4826 | E11: -0.024788572 | F11: 0.17167832
B12: авг | C12: 27909.468 | D12: 5318.105 | E12: 0.19054842 | F12: 0.13104575
B13: сен | C13: 81777.351 | D13: 8328.0994 | E13: 0.1018387 | F13: 0.15996269
B14: окт | C14: 31453.393 | D14: 3448.2573 | E14: 0.10963069 | F14: 0.16006289
B15: ноя | C15: 78628.717 | D15: 9292.1269 | E15: 0.11817727 | F15: 0.15116352
B16: дек | C16: 69545.62 | D16: 8983.5699 | E16: 0.12917521 | F16: 0.19082734
A17: 2017 | B17: янв | C17: 18174.076 | D17: -3281.007 | E17: -0.18053226 | F17: 0.17793103
B18: фев | C18: 11951.411 | D18: 2813.8508 | E18: 0.23544089 | F18: 0.1296875
B19: мар | C19: 38726.252 | D19: 9732.0978 | E19: 0.25130492 | F19: 0.14014493
B20: апр | C20: 34195.208 | D20: 4187.4962 | E20: 0.12245857 | F20: 0.1759375
B21: май | C21: 30131.686 | D21: 4667.869 | E21: 0.15491562 | F21: 0.16609589
B22: июн | C22: 24797.292 | D22: 3335.5572 | E22: 0.13451296 | F22: 0.17246377
B23: июл | C23: 28765.325 | D23: 3288.6483 | E23: 0.11432683 | F23: 0.17035714
B24: авг | C24: 36898.332 | D24: 5355.8084 | E24: 0.14515042 | F24: 0.15641509
B25: сен | C25: 64595.918 | D25: 8209.1627 | E25: 0.12708485 | F25: 0.14095563
B26: окт | C26: 31404.924 | D26: 2817.366 | E26: 0.089710965 | F26: 0.1623494
B27: ноя | C27: 75972.564 | D27: 12474.788 | E27: 0.16420123 | F27: 0.16231481
B28: дек | C28: 74919.521 | D28: 8016.9659 | E28: 0.1070077 | F28: 0.13724684
A29: 2018 | B29: янв | C29: 18542.491 | D29: 2824.8233 | E29: 0.15234325 | F29: 0.13258427
B30: фев | C30: 22978.815 | D30: 5004.5795 | E30: 0.21779102 | F30: 0.096385542
B31: мар | C31: 51715.875 | D31: 3611.968 | E31: 0.069842539 | F31: 0.19092025
B32: апр | C32: 38750.039 | D32: 2977.8149 | E32: 0.076846759 | F32: 0.15588235
B33: май | C33: 56987.728 | D33: 8662.1464 | E33: 0.15200021 | F33: 0.18444444
B34: июн | C34: 40344.534 | D34: 4750.3781 | E34: 0.11774527 | F34: 0.13869347
B35: июл | C35: 39261.963 | D35: 4432.8779 | E35: 0.11290515 | F35: 0.15945274
B36: авг | C36: 31115.374 | D36: 2062.0693 | E36: 0.066271718 | F36: 0.185625
B37: сен | C37: 73410.025 | D37: 9328.6576 | E37: 0.12707607 | F37: 0.14942149
B38: окт | C38: 59687.745 | D38: 16243.143 | E38: 0.2721353 | F38: 0.14719388
B39: ноя | C39: 79411.966 | D39: 4011.4075 | E39: 0.050513892 | F39: 0.15762162
B40: дек | C40: 96999.043 | D40: 17885.309 | E40: 0.18438645 | F40: 0.13542614
A41: 2019 | B41: янв | C41: 43971.374 | D41: 7140.4391 | E41: 0.16238836 | F41: 0.16129032
B42: фев | C42: 20301.133 | D42: 1613.872 | E42: 0.079496645 | F42: 0.18196262
B43: мар | C43: 58872.353 | D43: 14751.891 | E43: 0.25057418 | F43: 0.13084034
B44: апр | C44: 36521.536 | D44: 933.29 | E44: 0.025554511 | F44: 0.1944335
B45: май | C45: 44261.11 | D45: 6342.5828 | E45: 0.14329923 | F45: 0.15243802
B46: июн | C46: 52981.726 | D46: 8223.3357 | E46: 0.15521079 | F46: 0.17191837
B47: июл | C47: 45264.416 | D47: 6952.6212 | E47: 0.15360015 | F47: 0.14004425
B48: авг | C48: 63120.888 | D48: 9040.9557 | E48: 0.14323239 | F48: 0.14357798
B49: сен | C49: 87866.652 | D49: 10991.556 | E49: 0.1250936 | F49: 0.14738562
B50: окт | C50: 77776.923 | D50: 9275.2755 | E50: 0.11925485 | F50: 0.17422819
B51: ноя | C51: 118447.83 | D51: 9690.1037 | E51: 0.081809047 | F51: 0.16098039
B52: дек | C52: 83829.319 | D52: 8483.3468 | E52: 0.10119785 | F52: 0.14658009
A53: Общий итог | C53: 2297200.9 | D53: 286397.02 | E53: 0.12467217 | F53: 0.15620272

Sheet Продажи по штатам
A3: Сумма по полю Sales
A4: State | B4: Итог
A5: North Dakota | B5: 919.91
A6: West Virginia | B6: 1209.824
A7: Maine | B7: 1270.53
A8: South Dakota | B8: 1315.56
A9: Wyoming | B9: 1603.136
A10: District of Columbia | B10: 2865.02
A11: Kansas | B11: 2914.31
A12: Idaho | B12: 4382.486
A13: Iowa | B13: 4579.76
A14: New Mexico | B14: 4783.522
A15: Montana | B15: 5589.352
A16: New Hampshire | B16: 7292.524
... A54: Общий итог | B54: 2297200.9

Sheet Продажи по регионам
A3: Сумма по полю Sales
A4: Region | B4: Итог
A5: Central | B5: 0.21819594
A6: East | B6: 0.29548188
A7: South | B7: 0.1705214
A8: West | B8: 0.31580078
A9: Общий итог | B9: 1

Sheet Возвраты
A3: Сумма по полю Sales
A4: Returnes | B4: Итог
A5: No | B5: 0.92142425
A6: Yes | B6: 0.078575749
A7: Общий итог | B7: 1

Sheet Дашборд
A1: SUPERSTORE SAMPLE DASHBOARD
E2: Ключевые метрики
E3: Total Sales | F3: =SUM('Основные показатели'!C5:C52) -> 2297200.9
E4: Total Profit | F4: =SUM('Основные показатели'!D5:D52) -> 286397.02
E5: Profit Ratio | F5: =F4/F3 -> 0.12467217
E6: Avg. Discount | F6: =AVERAGE('Основные показатели'!F5:F52) -> 0.15632258
